[{"單號":"BY202201210009","料號":"T2310-02Y","品名":"T231三角板毛件","數量":"1134","來源廠商":"守宬","日期":"2022/01/22","下一關":"待發","地區":"3F","行號":"2"},{"單號":"BY202202110020","料號":"S2680-25Y","品名":"(可代S2670-25Y) S268滑座毛件","數量":"345","來源廠商":"伍輝","日期":"2022/02/14","下一關":"待發90KG","地區":"加工","行號":"1"},{"單號":"BY202201250017","料號":"P1160-28X","品名":"P116鋁柄鑄件","數量":"2000","來源廠商":"億峰富(蕎鋒)","日期":"2022/01/26","下一關":"同偉行","地區":"5F","行號":"2"},{"單號":"BY202201250013","料號":"P2400B-01Y","品名":"3!P240藍本台毛件","數量":"1281","來源廠商":"冠承","日期":"2022/01/26","下一關":"同偉行","地區":"5F","行號":"2"},{"單號":"MK202107010223","料號":"CA870-90","品名":"CA870橫管","數量":"50","來源廠商":"元貝","日期":"2021/08/11","下一關":"待發","地區":"5F","行號":"1"},{"單號":"BY202112290016","料號":"H3050-03B-X","品名":"H305直刀彎鐵管7/8*2.0*395毛件","數量":"1000","來源廠商":"鴻隆慶","日期":"2021/12/29","下一關":"待發","地區":"5F","行號":"2"},{"單號":"BY202012070042","料號":"PD460-07","品名":"1!!PD460底座薄板","數量":"140","來源廠商":"靖盈","日期":"2020/12/09","下一關":"待發","地區":"5F","行號":"2"},{"單號":"AJ202003310001","料號":"PD410-15","品名":"PD410平壓紙板(光板或酸洗板)","數量":"193","來源廠商":"盤盈","日期":"2020/03/21","下一關":"待發","地區":"3F","行號":"2"},{"單號":"AJ202003310001","料號":"S2270-01","品名":"#S227本台鑄件YBICO","數量":"25","來源廠商":"盤盈","日期":"2020/03/31","下一關":"待發","地區":"待發","行號":"3"},{"單號":"AJ202003310001","料號":"P4820-12","品名":"(用完改P4820-47) P482四角阻齒(90度)","數量":"13","來源廠商":"盤盈","日期":"2020/03/31","下一關":"待發","地區":"待發","行號":"3"},{"單號":"AJ202003310001","料號":"P2700H-01Y","品名":"P270黑手柄毛組件","數量":"1","來源廠商":"盤盈","日期":"2020/03/31","下一關":"待發","地區":"待發","行號":"3"},{"單號":"AJ202003310001","料號":"P3100H-28Y","品名":"(可用P3000H-28Y)P310黑手柄毛件","數量":"4","來源廠商":"盤盈","日期":"2020/03/31","下一關":"待發","地區":"待發","行號":"3"},{"單號":"AJ202003310001","料號":"P1080-26Y","品名":"1!!P108滑座組件毛件(短心電錏)YBICO","數量":"9","來源廠商":"盤盈","日期":"2020/03/31","下一關":"待發","地區":"待發","行號":"3"},{"單號":"AJ202003310001","料號":"P2680-02X","品名":"P268本台鑄件","數量":"1","來源廠商":"盤盈","日期":"2020/03/31","下一關":"待發","地區":"待發","行號":"3"},{"單號":"BY202012070042","料號":"PD460-07","品名":"1!!PD460底座薄板","數量":"61","來源廠商":"靖盈","日期":"2020/12/09","下一關":"待發","地區":"3F","行號":"2"},{"單號":"IO202102250012","料號":"PD110-26","品名":"1!P110平壓紙板+有齒刀片組件","數量":"30","來源廠商":"其他入庫","日期":"2019/06/13","下一關":"待發","地區":"3F","行號":"1"},{"單號":"BY202011090056","料號":"PD460-44Y","品名":"PD460吊架中段連接管毛件","數量":"30","來源廠商":"鴻隆慶","日期":"2020/12/15","下一關":"待發","地區":"3F","行號":"1"},{"單號":"BY202102180024","料號":"H3050-02B-X","品名":"H305連桿直鐵管毛件7/8*405*2.0mm厚","數量":"635","來源廠商":"鴻隆慶","日期":"2021/02/19","下一關":"待發","地區":"5F","行號":"1"},{"單號":"BY202112240048","料號":"P2420-36X","品名":"1!!P242刀管毛件(車兩溝小孔)","數量":"2100","來源廠商":"將材","日期":"2021/12/24","下一關":"待發","地區":"5F","行號":"1"},{"單號":"BY202107210037","料號":"CA320-09X","品名":"CA320L型鐵管毛件1*604*T1.8mm","數量":"100","來源廠商":"鴻隆慶","日期":"2021/07/20","下一關":"待發","地區":"5F","行號":"1"},{"單號":"BY202108260012","料號":"CA320-09X","品名":"CA320L型鐵管毛件1*604*T1.8mm","數量":"100","來源廠商":"鴻隆慶","日期":"2021/08/26","下一關":"待發","地區":"5F","行號":"1"},{"單號":"BY202108260011","料號":"CA320-08X","品名":"CA320車輪鐵管毛件7/8*380*T1.5mm","數量":"200","來源廠商":"鴻隆慶","日期":"2021/08/26","下一關":"待發","地區":"5F","行號":"1"},{"單號":"BY202105240031","料號":"CA790-26","品名":"底圓管(OD70*89*T1.6mm)","數量":"100","來源廠商":"鴻隆慶","日期":"2021/05/21","下一關":"待發","地區":"5F","行號":"1"},{"單號":"AJ202003310001","料號":"PQ200-37X","品名":"1!!PQ200刀心料件(OD14.25*75.2mmL)","數量":"1062","來源廠商":"盤盈","日期":"2020/03/31","下一關":"待發","地區":"加工","行號":"1"},{"單號":"AJ202003310001","料號":"PQ200-36X","品名":"1!!PQ200刀管毛件(車兩溝小孔)","數量":"1036","來源廠商":"盤盈","日期":"2020/03/31","下一關":"待發","地區":"加工","行號":"1"},{"單號":"BY202108250018","料號":"P1171-12X","品名":"P1171四角阻齒鑄件(S25C)","數量":"5250","來源廠商":"沿峰","日期":"2021/08/25","下一關":"待發","地區":"加工","行號":"1"},{"單號":"MK202109020004","料號":"P4000-11X","品名":"P400腳踏鑄件","數量":"802","來源廠商":"同偉行","日期":"2021/09/30","下一關":"待發","地區":"加工","行號":"1"},{"單號":"AJ202003310001","料號":"P2600-10X","品名":"1!!P260刀心料件(OD12.2*74mm)","數量":"5210","來源廠商":"盤盈","日期":"2020/03/31","下一關":"待發","地區":"加工","行號":"2"},{"單號":"MK202105190114","料號":"SL201-57","品名":"SL201花輪把手","數量":"34","來源廠商":"鴻鎰","日期":"2021/10/28","下一關":"待發","地區":"加工","行號":"1"},{"單號":"AJ202003310001","料號":"P5800-23Y","品名":"1!!P580刀心毛件","數量":"280","來源廠商":"盤盈","日期":"2020/03/31","下一關":"待發","地區":"加工","行號":"2"},{"單號":"BY202011160007","料號":"PD460-04Y","品名":"1!!PD460橫角鐵毛件","數量":"300","來源廠商":"鴻隆慶","日期":"2020/11/16","下一關":"待發","地區":"加工","行號":"1"},{"單號":"BY202105070030","料號":"PE1025-42","品名":"PE1025凸輪柄(4140材質)","數量":"52","來源廠商":"伍輝","日期":"2021/05/10","下一關":"待發","地區":"待發","行號":"4"},{"單號":"BY202106080012","料號":"PQ300-28X","品名":"手柄鑄件","數量":"17","來源廠商":"晟寶","日期":"2021/06/08","下一關":"同偉行","地區":"加工","行號":"5"},{"單號":"MK202106280064","料號":"YC310-12Y","品名":"YC310連桿鐵管柄組件毛件","數量":"3","來源廠商":"森太","日期":"2021/06/22","下一關":"同偉行","地區":"加工","行號":"5"},{"單號":"IO202005310018","料號":"CT500-13X","品名":"CT500刀片毛件","數量":"1150","來源廠商":"其他入庫","日期":"2020/07/02","下一關":"待發","地區":"加工","行號":"5"},{"單號":"IO202102250002","料號":"S2200-03X","品名":"S220本台鑄件(YBICO)","數量":"18","來源廠商":"其他入庫","日期":"2021/02/25","下一關":"待發","地區":"加工","行號":"5"},{"單號":"AJ202003310001","料號":"P5800N-02Y","品名":"1!!P580電鎳鐵本台毛件","數量":"167","來源廠商":"盤盈","日期":"2020/03/31","下一關":"待發","地區":"加工","行號":"5"},{"單號":"AJ202003310001","料號":"P2700H-01Y","品名":"P270黑手柄毛組件","數量":"5","來源廠商":"盤盈","日期":"2020/03/31","下一關":"待發","地區":"待發","行號":"3"},{"單號":"查無單號","料號":"P2420-37Y","品名":"1!!P242刀心毛件(70.5mmL)S45C","數量":"2265","來源廠商":"里祥","日期":"2021/08/30","下一關":"待發","地區":"加工","行號":"2"},{"單號":"BY202112280024","料號":"C3226-10","品名":"C3226手柄頭(8620)","數量":"9","來源廠商":"伍輝","日期":"2021/02/17","下一關":"同偉行","地區":"加工","行號":"6"},{"單號":"BY202111260021","料號":"H2300-12X","品名":"1!!H230小刀片鍛件(YBICO)","數量":"989","來源廠商":"鐵益(鐵皇)","日期":"2021/11/26","下一關":"待發","地區":"待發","行號":"3"},{"單號":"BY202102050012","料號":"H2110-12X","品名":"1!!H211小刀片鍛件(YBICO)","數量":"65","來源廠商":"鐵益(鐵皇)","日期":"2021/02/05","下一關":"待發","地區":"加工","行號":"2"},{"單號":"BY202111250001","料號":"H2110-12X","品名":"1!!H211小刀片鍛件(YBICO)","數量":"1000","來源廠商":"鐵益(鐵皇)","日期":"2021/11/26","下一關":"待發","地區":"待發","行號":"3"},{"單號":"BY202111250001","料號":"H2110-12X","品名":"1!!H211小刀片鍛件(YBICO)","數量":"1000","來源廠商":"鐵益(鐵皇)","日期":"2021/11/26","下一關":"待發","地區":"待發","行號":"3"},{"單號":"BY202112010001","料號":"H2110-110-X","品名":"1!!H211大刀片鍛件(無YBICO)","數量":"700","來源廠商":"鐵益(鐵皇)","日期":"2021/12/01","下一關":"待發","地區":"待發","行號":"3"},{"單號":"BY202112010001","料號":"H2110-110-X","品名":"1!!H211大刀片鍛件(無YBICO)","數量":"870","來源廠商":"鐵益(鐵皇)","日期":"2021/12/01","下一關":"待發","地區":"待發","行號":"3"},{"單號":"BY202112010001","料號":"H2110-110-X","品名":"1!!H211大刀片鍛件(無YBICO)","數量":"700","來源廠商":"鐵益(鐵皇)","日期":"2021/12/01","下一關":"待發","地區":"待發","行號":"3"},{"單號":"BY202112010001","料號":"H2110-110-X","品名":"1!!H211大刀片鍛件(無YBICO)","數量":"100","來源廠商":"鐵益(鐵皇)","日期":"2021/12/01","下一關":"待發","地區":"待發","行號":"3"},{"單號":"AJ202003310001","料號":"PD110-02X","品名":"1!PD110台架鐵管毛件(外雙倒角)","數量":"30","來源廠商":"盤盈","日期":"2020/03/31","下一關":"待發","地區":"5F","行號":"2"},{"單號":"BY202104270012","料號":"PD403-02X","品名":"PD403本體台架毛件","數量":"64","來源廠商":"鴻隆慶","日期":"2021/04/27","下一關":"待發","地區":"5F","行號":"2"},{"單號":"BY202106230007","料號":"PD403-02X","品名":"PD403本體台架毛件","數量":"16","來源廠商":"鴻隆慶","日期":"2021/06/22","下一關":"森太","地區":"5F","行號":"2"},{"單號":"AJ202003310001","料號":"PD410-21X","品名":"PD410台架連結管毛件","數量":"50","來源廠商":"盤盈","日期":"2020/03/31","下一關":"待發","地區":"5F","行號":"2"},{"單號":"BY202112030001","料號":"AC120-04","品名":"AC120固定架","數量":"182","來源廠商":"守宬(展昕)","日期":"2021/12/03","下一關":"森太","地區":"加工","行號":"2"},{"單號":"BY202202250007","料號":"CA870-90Y","品名":"CA870橫管毛件口32*1.5T*1100mmL","數量":"100","來源廠商":"鴻隆慶","日期":"2022/03/03","下一關":"同偉行","地區":"3F","行號":"2"},{"單號":"BY202010280043","料號":"PD460-03Y","品名":"1!!PD460扁鐵管毛件","數量":"200","來源廠商":"鴻隆慶","日期":"2020/11/05","下一關":"待發","地區":"5F","行號":"1"},{"單號":"BY202203030002","料號":"T5360-04Y","品名":"T536鐵板毛件","數量":"1100","來源廠商":"卯勝","日期":"2022/03/08","下一關":"待發","地區":"5F","行號":"2"},{"單號":"BY202203030002","料號":"T5360-04Y","品名":"T536鐵板毛件","數量":"1100","來源廠商":"卯勝","日期":"2022/03/08","下一關":"待發","地區":"5F","行號":"2"},{"單號":"B1","料號":"CA660-01","品名":"1!CA660台架組件毛件","數量":"37","來源廠商":"山杰","日期":"2021/09/08","下一關":"待發","地區":"B1-A","行號":"2"},{"單號":"B1","料號":"CA276H-38","品名":"#CA276黑公帶盤組件","數量":"75","來源廠商":"鴻鎰","日期":"2021/08/04","下一關":"待發","地區":"B1-A","行號":"2"},{"單號":"B1","料號":"CA870H-86","品名":"#CA870黑吊架上支撐管組件","數量":"120","來源廠商":"山杰","日期":"2021/10/15","下一關":"待發","地區":"B1-A","行號":"2"},{"單號":"B1","料號":"CA276H-54Y","品名":"#CA276黑母帶盤組件(YBICO)","數量":"94","來源廠商":"鴻鎰","日期":"2021/08/04","下一關":"待發","地區":"B1-A","行號":"2"},{"單號":"B1","料號":"CA870H-94","品名":"#CA870黑加強管組件","數量":"123","來源廠商":"山杰","日期":"2022/01/05","下一關":"待發","地區":"B1-A","行號":"2"},{"單號":"B1","料號":"CA670-01","品名":"#CA670台架組件","數量":"12","來源廠商":"山杰","日期":"2021/11/03","下一關":"待發","地區":"B1-A","行號":"4"},{"單號":"B1","料號":"CA276H-52","品名":"#CA276黑母帶盤組件","數量":"55","來源廠商":"鴻鎰","日期":"2021/09/05","下一關":"待發","地區":"B1-A","行號":"3"},{"單號":"B1","料號":"CA670-01","品名":"#CA670台架組件","數量":"12","來源廠商":"山杰","日期":"2021/11/04","下一關":"待發","地區":"B1-A","行號":"3"},{"單號":"B1","料號":"CA650Y-51","品名":"外側鐵板(黃123C)","數量":"34","來源廠商":"鴻鎰","日期":"2021/10/12","下一關":"待發","地區":"B1-A","行號":"4"},{"單號":"B1","料號":"CA650Y-51","品名":"外側鐵板(黃123C)","數量":"75","來源廠商":"鴻鎰","日期":"2021/10/12","下一關":"待發","地區":"B1-A","行號":"3"},{"單號":"B1","料號":"CA652Y-31","品名":"中隔板(黃123C)","數量":"68","來源廠商":"鴻鎰","日期":"2020/03/31","下一關":"待發","地區":"B1-A","行號":"4"},{"單號":"B1","料號":"CA652-31","品名":"中隔板(黑色)","數量":"51","來源廠商":"鴻鎰","日期":"2021/08/20","下一關":"待發","地區":"B1-A","行號":"4"},{"單號":"B1","料號":"CA120Z-47","品名":"#CA120橘(166C)母帶盤OD616mm","數量":"124","來源廠商":"鴻鎰","日期":"2022/02/24","下一關":"待發","地區":"B1-A","行號":"4"},{"單號":"BY202203090033","料號":"CB327H-06","品名":"#CB327黑台架組件","數量":"48","來源廠商":"山杰","日期":"2022/03/10","下一關":"B1","地區":"B1-D","行號":"4"},{"單號":"BY202203090005","料號":"CA720-47","品名":"#黑母帶盤400*635mm單層","數量":"200","來源廠商":"鴻鎰","日期":"2022/03/09","下一關":"B1","地區":"B1-D","行號":"4"},{"單號":"BY202203090005","料號":"CA500-47","品名":"#CA500黑母帶盤ID400*635mm單層","數量":"92","來源廠商":"鴻鎰","日期":"2022/03/09","下一關":"B1","地區":"B1-D","行號":"4"},{"單號":"BY202203090005","料號":"CA200H-51","品名":"#CA200黑公帶盤組件ID200*OD500mm(4小孔","數量":"21","來源廠商":"鴻鎰","日期":"2022/03/09","下一關":"B1","地區":"B1-A","行號":"5"},{"單號":"BY202203100016","料號":"CA310H-30","品名":"黑無大孔小工具盒(無YBICO)","數量":"158","來源廠商":"山杰","日期":"2022/03/10","下一關":"B1","地區":"B1-A","行號":"6"},{"單號":"BY202203100016","料號":"CA310H-30","品名":"黑無大孔小工具盒(無YBICO)","數量":"25","來源廠商":"山杰","日期":"2022/03/10","下一關":"B1","地區":"B1-A","行號":"6"},{"單號":"B1","料號":"CA720-41","品名":"#黑公帶盤組400*OD635mm","數量":"60","來源廠商":"鴻鎰","日期":"2021/11/15","下一關":"待發","地區":"B1-A","行號":"4"},{"單號":"B1","料號":"CA720-41","品名":"#黑公帶盤組400*OD635mm","數量":"32","來源廠商":"鴻鎰","日期":"2021/11/15","下一關":"待發","地區":"B1-A","行號":"4"},{"單號":"B1","料號":"CA500Y-41","品名":"#CA500黃公帶盤組件","數量":"47","來源廠商":"鴻鎰","日期":"2021/06/07","下一關":"待發","地區":"B1-A","行號":"6"},{"單號":"B1","料號":"CA120Z-51","品名":"#CA120橘(166C)公帶盤組件OD616mm(4小孔)","數量":"93","來源廠商":"鴻鎰","日期":"2022/03/01","下一關":"待發","地區":"B1-A","行號":"4"},{"單號":"B1","料號":"CA500Y-47","品名":"#CA500黃母帶盤","數量":"49","來源廠商":"鴻鎰","日期":"2021/06/18","下一關":"待發","地區":"B1-A","行號":"6"},{"單號":"B1","料號":"CC100H-03","品名":"#CC100轉輪組件(黑烤漆)","數量":"10","來源廠商":"山杰","日期":"2021/08/23","下一關":"待發","地區":"B1-B","行號":"1"},{"單號":"B1","料號":"CC100H-03","品名":"#CC100轉輪組件(黑烤漆)","數量":"4","來源廠商":"山杰","日期":"2021/08/23","下一關":"待發","地區":"B1-B","行號":"1"},{"單號":"B1","料號":"CC100H-01","品名":"#CC100鐵管底座(黑烤漆)","數量":"3","來源廠商":"山杰","日期":"2021/10/12","下一關":"待發","地區":"B1-B","行號":"1"},{"單號":"B1","料號":"CA100Y-24","品名":"#黃母帶盤400mm*OD610mm","數量":"54","來源廠商":"鴻鎰","日期":"2021/10/14","下一關":"待發","地區":"B1-A","行號":"6"},{"單號":"B1","料號":"CA100Y-24","品名":"#黃母帶盤400mm*OD610mm","數量":"104","來源廠商":"鴻鎰","日期":"2021/10/14","下一關":"待發","地區":"B1-前棟","行號":"4"},{"單號":"B1","料號":"CA100Y-51","品名":"#CA100黃公帶盤組件ID200*OD610mm(4小孔","數量":"120","來源廠商":"鴻鎰","日期":"2021/11/02","下一關":"待發","地區":"B1-前棟","行號":"4"},{"單號":"B1","料號":"CA670-01","品名":"#CA670台架組件","數量":"8","來源廠商":"山杰","日期":"2021/11/03","下一關":"待發","地區":"B1-B","行號":"1"},{"單號":"B1","料號":"CA670-01","品名":"#CA670台架組件","數量":"12","來源廠商":"山杰","日期":"2021/11/03","下一關":"待發","地區":"B1-B","行號":"1"},{"單號":"B1","料號":"CA670-01","品名":"#CA670台架組件","數量":"12","來源廠商":"山杰","日期":"2021/11/03","下一關":"待發","地區":"B1-B","行號":"1"},{"單號":"B1","料號":"CA122Z-51","品名":"#CA122橘(166C)公帶盤組件OD500mm(4小孔)","數量":"64","來源廠商":"鴻鎰","日期":"2021/09/02","下一關":"待發","地區":"B1-B","行號":"1"},{"單號":"B1","料號":"CA122Z-47","品名":"#CA122橘(166C)母帶盤OD500mm","數量":"63","來源廠商":"鴻鎰","日期":"2021/08/14","下一關":"待發","地區":"B1-B","行號":"1"},{"單號":"B1","料號":"CC100H-02","品名":"#CC100底座固定管(黑烤漆)","數量":"25","來源廠商":"山杰","日期":"2021/08/23","下一關":"待發","地區":"B1-B","行號":"1"},{"單號":"B1","料號":"CA400Y-20","品名":"#黃公帶盤組件OD710mm","數量":"2","來源廠商":"鴻鎰","日期":"2020/03/31","下一關":"待發","地區":"B1-A","行號":"6"},{"單號":"B1","料號":"CA7242Y-41","品名":"#CA7242黃公帶盤組件","數量":"22","來源廠商":"鴻鎰","日期":"2020/03/31","下一關":"待發","地區":"B1-前棟","行號":"4"},{"單號":"B1","料號":"CA720Y-47","品名":"#黃母帶盤400*635mm單層","數量":"22","來源廠商":"鴻鎰","日期":"2020/03/31","下一關":"待發","地區":"B1-A","行號":"6"},{"單號":"B1","料號":"CA670-01","品名":"#CA670台架組件","數量":"12","來源廠商":"山杰","日期":"2021/11/03","下一關":"待發","地區":"B1-B","行號":"4"},{"單號":"B1","料號":"CA6501-51","品名":"CA6501外側鐵板(黑色)","數量":"106","來源廠商":"鴻鎰","日期":"2021/12/16","下一關":"待發","地區":"B1-B","行號":"2"},{"單號":"B1","料號":"CA6501-05","品名":"#CA6501台架組件","數量":"45","來源廠商":"山杰","日期":"2021/12/06","下一關":"待發","地區":"B1-B","行號":"2"},{"單號":"B1","料號":"CA650-05","品名":"#CA650黑台架組件","數量":"33","來源廠商":"山杰","日期":"2021/11/25","下一關":"待發","地區":"B1-A","行號":"3"},{"單號":"B1","料號":"CA670-01","品名":"#CA670台架組件","數量":"12","來源廠商":"山杰","日期":"2021/11/03","下一關":"待發","地區":"B1-B","行號":"5"},{"單號":"B1","料號":"CA670-01","品名":"#CA670台架組件","數量":"12","來源廠商":"山杰","日期":"2021/11/03","下一關":"待發","地區":"B1-B","行號":"5"},{"單號":"B1","料號":"CA760H-02","品名":"#CA760黑特大工具盒","數量":"44","來源廠商":"鴻鎰","日期":"2022/02/24","下一關":"待發","地區":"B1-A","行號":"6"},{"單號":"B1","料號":"CA520H-020","品名":"#CA520黑手柄大工具盒組件(無YBICO)","數量":"6","來源廠商":"鴻鎰","日期":"2021/09/22","下一關":"待發","地區":"B1-B","行號":"4"},{"單號":"B1","料號":"CA920H-01","品名":"#CA920黑工具箱組件(黑平光)","數量":"83","來源廠商":"鴻鎰","日期":"2022/01/19","下一關":"待發","地區":"B1-B","行號":"3"},{"單號":"B1","料號":"CA851H-10","品名":"#CA851黑手柄工具盒組件","數量":"29","來源廠商":"鴻鎰","日期":"2021/12/08","下一關":"待發","地區":"B1-B","行號":"3"},{"單號":"B1","料號":"CA500H-01","品名":"#CA500黑手柄工具盒組件(無YB有彈簧桿)","數量":"32","來源廠商":"鴻鎰","日期":"2021/12/17","下一關":"待發","地區":"B1-B","行號":"3"},{"單號":"B1","料號":"CA202-24","品名":"#黑母帶盤ID195mm*500mm單層","數量":"37","來源廠商":"鴻鎰","日期":"2020/10/21","下一關":"待發","地區":"B1-B","行號":"4"},{"單號":"B1","料號":"CA850H-10","品名":"#CA850黑手柄工具盒組件","數量":"15","來源廠商":"鴻鎰","日期":"2022/02/18","下一關":"待發","地區":"B1-B","行號":"6"},{"單號":"B1","料號":"CA850H-58","品名":"#外側黑帶盤OD650單孔","數量":"66","來源廠商":"鴻鎰","日期":"2022/01/19","下一關":"待發","地區":"B1-A","行號":"5"},{"單號":"B1","料號":"CA850H-60","品名":"#內側黑帶盤OD650(4孔)","數量":"68","來源廠商":"鴻鎰","日期":"2022/02/18","下一關":"待發","地區":"B1-A","行號":"5"},{"單號":"BY202203140029","料號":"S2910-03X","品名":"S291本台鑄件(無YBICO)","數量":"43","來源廠商":"晟寶","日期":"2022/03/16","下一關":"待發","地區":"加工","行號":"2"},{"單號":"B1","料號":"CA324H-06","品名":"#CA324黑台架組件(無焊帶盤心焊橢圓底管)","數量":"88","來源廠商":"山杰","日期":"2021/12/03","下一關":"待發","地區":"B1-A","行號":"5"},{"單號":"B1","料號":"CA2535Z-51","品名":"#CA2535橘公帶盤組件(OD500mm)","數量":"200","來源廠商":"鴻鎰","日期":"2022/02/24","下一關":"待發","地區":"B1-D","行號":"4"},{"單號":"B1","料號":"CA2535Z-47","品名":"#CA2535橘母帶盤OD500mm","數量":"200","來源廠商":"鴻鎰","日期":"2022/02/24","下一關":"待發","地區":"B1-D","行號":"4"},{"單號":"B1","料號":"CA7242Z-41","品名":"#CA7242橘公帶盤組件","數量":"21","來源廠商":"鴻鎰","日期":"2022/02/24","下一關":"待發","地區":"B1-B","行號":"1"},{"單號":"B1","料號":"CA920H-01","品名":"#CA920黑工具箱組件(黑平光)","數量":"5","來源廠商":"鴻鎰","日期":"2022/01/18","下一關":"待發","地區":"B1-B","行號":"3"},{"單號":"B1","料號":"CA322-06","品名":"#CA322台架組件(無焊帶盤心可穿帶)","數量":"12","來源廠商":"山杰","日期":"2021/12/03","下一關":"待發","地區":"B1-B","行號":"6"},{"單號":"B1","料號":"CA870H-25","品名":"#CA870黑工具盒連手柄組件","數量":"36","來源廠商":"山杰","日期":"2021/12/28","下一關":"待發","地區":"B1-C","行號":"7"},{"單號":"B1","料號":"CA432H-02","品名":"#CA432黑手柄組件","數量":"33","來源廠商":"鴻鎰","日期":"2021/11/01","下一關":"待發","地區":"B1-D","行號":"3"},{"單號":"B1","料號":"CA750-01","品名":"#台架組件","數量":"44","來源廠商":"鴻鎰","日期":"2021/10/13","下一關":"待發","地區":"B1-D","行號":"3"},{"單號":"B1","料號":"CB327H-010","品名":"#(可用CA320-010)CB327黑手柄工具盒組件(柄孔14mm)NO YBICO","數量":"90","來源廠商":"山杰","日期":"2021/05/28","下一關":"待發","地區":"B1-D","行號":"3"},{"單號":"B1","料號":"CA320-01","品名":"#(可用CB327H-01)手柄工具盒組件YBICO 焊接不同CA100(柄孔10mm)","數量":"82","來源廠商":"山杰","日期":"2021/05/31","下一關":"待發","地區":"B1-D","行號":"3"},{"單號":"B1","料號":"CB327H-01","品名":"#(可用CA320-01)CB327黑手柄工具盒組件(柄孔14mm)","數量":"44","來源廠商":"鴻鎰","日期":"2022/03/08","下一關":"待發","地區":"B1-D","行號":"3"},{"單號":"B1","料號":"CA670-01","品名":"#CA670台架組件","數量":"14","來源廠商":"山杰","日期":"2021/11/13","下一關":"待發","地區":"B1-B","行號":"1"},{"單號":"B1","料號":"CA870H-80","品名":"#CA870黑吊架下支撐管組件","數量":"117","來源廠商":"山杰","日期":"2021/10/15","下一關":"待發","地區":"B1-B","行號":"5"},{"單號":"BY202203220017","料號":"H1000-12X","品名":"小刀片鍛件(中碳)","數量":"2340","來源廠商":"世鎰","日期":"2022/03/23","下一關":"待發","地區":"加工","行號":"3"},{"單號":"BY202203150047","料號":"CA500-41","品名":"#CA500黑公帶盤組件400mm","數量":"46","來源廠商":"鴻鎰","日期":"2022/03/16","下一關":"B1","地區":"B1-備料","行號":"無"},{"單號":"BY202203150047","料號":"CA400H-25","品名":"#CA400黑母帶盤組件OD710mm","數量":"64","來源廠商":"鴻鎰","日期":"2022/03/16","下一關":"B1","地區":"B1-備料","行號":"無"},{"單號":"BY202203180027","料號":"CA400H-01","品名":"#CA400黑台架組件焊帶盤心(無YBICO)","數量":"20","來源廠商":"山杰","日期":"2022/03/21","下一關":"B1","地區":"B1-C","行號":"5"},{"單號":"BY202203180027","料號":"CA400H-01","品名":"#CA400黑台架組件焊帶盤心(無YBICO)","數量":"24","來源廠商":"山杰","日期":"2022/03/21","下一關":"B1","地區":"B1-C","行號":"5"},{"單號":"BY202203180027","料號":"CA400H-01","品名":"#CA400黑台架組件焊帶盤心(無YBICO)","數量":"20","來源廠商":"山杰","日期":"2022/03/21","下一關":"B1","地區":"B1-C","行號":"7"},{"單號":"BY202203180027","料號":"CA400H-01","品名":"#CA400黑台架組件焊帶盤心(無YBICO)","數量":"16","來源廠商":"山杰","日期":"2022/03/21","下一關":"B1","地區":"B1-C","行號":"5"},{"單號":"BY202203250027","料號":"S2670-11X","品名":"S267前座鑄件","數量":"1889","來源廠商":"永山宏","日期":"2022/03/28","下一關":"待發","地區":"加工","行號":"2"},{"單號":"B1","料號":"CA243-25","品名":"塑膠盤495mm*62mm 孔15.3mm","數量":"91","來源廠商":"辰鑫","日期":"2020/03/31","下一關":"待發","地區":"B1-A","行號":"4"},{"單號":"B1","料號":"CA276-58","品名":"1!CA276塑膠工具盒(有YBICO)","數量":"37","來源廠商":"保陞","日期":"2020/03/31","下一關":"待發","地區":"B1-A","行號":"3"},{"單號":"B1","料號":"CA258B-42","品名":"#CA258藍301公帶盤組件OD500mm","數量":"31","來源廠商":"鴻鎰","日期":"2020/03/31","下一關":"待發","地區":"B1-C","行號":"7"},{"單號":"B1","料號":"CA258B-47","品名":"#CA258藍(301)母帶盤OD500mm","數量":"33","來源廠商":"鴻鎰","日期":"2020/03/31","下一關":"待發","地區":"B1-C","行號":"7"},{"單號":"BY202112060013","料號":"CA6501-05","品名":"#CA6501台架組件","數量":"25","來源廠商":"山杰","日期":"2022/03/25","下一關":"B1","地區":"B1-B","行號":"2"},{"單號":"BY202203250024","料號":"E6280-18Y","品名":"E628輸出軸車件","數量":"1044","來源廠商":"將材","日期":"2022/03/29","下一關":"晶幃","地區":"加工","行號":"3"},{"單號":"B1","料號":"CA310-15R","品名":"#(用完改CA310-16C)無大孔小工具盒CARISTRAP)(黑平光)","數量":"125","來源廠商":"山杰","日期":"2020/03/31","下一關":"待發","地區":"B1-前棟","行號":"4"},{"單號":"BY202204010001","料號":"CA500H-01Y","品名":"#CA500黑手柄工具盒組件YBICO(有彈簧桿)","數量":"36","來源廠商":"鴻鎰","日期":"2022/04/07","下一關":"B1","地區":"B1-B","行號":"4"},{"單號":"BY202104230030","料號":"PA470-133-Y","品名":"PA470刀管車件","數量":"176","來源廠商":"將材","日期":"2022/04/12","下一關":"伍輝","地區":"待發","行號":"3"},{"單號":"MK202112090047","料號":"P2600-01Y","品名":"P260手柄毛件","數量":"3000","來源廠商":"元貝","日期":"2022/04/08","下一關":"B1待發","地區":"B1-C","行號":"3"},{"單號":"BY202204060010","料號":"CA850H-01","品名":"#CA850黑台架組組件","數量":"42","來源廠商":"鴻鎰","日期":"2022/04/07","下一關":"B1","地區":"B1-A","行號":"3"},{"單號":"BY202204130016","料號":"H3040-12X","品名":"H304小刀片鍛件(NO YBICO)","數量":"1200","來源廠商":"良璂","日期":"2022/04/14","下一關":"待發","地區":"待發","行號":"3"},{"單號":"BY202204130016","料號":"H3040-12X","品名":"H304小刀片鍛件(NO YBICO)","數量":"1200","來源廠商":"良璂","日期":"2022/04/14","下一關":"待發","地區":"待發","行號":"3"},{"單號":"BY202201240016","料號":"H3050-15X","品名":"H305直刀鍛件(中鋼鉻釩)(打2)","數量":"442","來源廠商":"鐵益(鐵皇)","日期":"2022/01/26","下一關":"待發","地區":"待發","行號":"2"},{"單號":"BY202201240016","料號":"H3050-15X","品名":"H305直刀鍛件(中鋼鉻釩)(打2)","數量":"700","來源廠商":"鐵益(鐵皇)","日期":"2022/01/26","下一關":"待發","地區":"待發","行號":"4"},{"單號":"BY202201240016","料號":"H3050-15X","品名":"H305直刀鍛件(中鋼鉻釩)(打2)","數量":"700","來源廠商":"鐵益(鐵皇)","日期":"2022/01/26","下一關":"待發","地區":"待發","行號":"4"},{"單號":"BY202204150031","料號":"H1000-12X","品名":"小刀片鍛件(中碳)","數量":"1742","來源廠商":"世鎰","日期":"2022/04/19","下一關":"待發","地區":"加工","行號":"3"},{"單號":"BY202204150031","料號":"H1000-11X","品名":"大刀片鍛件(中碳)無YBICO","數量":"1169","來源廠商":"世鎰","日期":"2022/04/19","下一關":"待發","地區":"加工","行號":"1"},{"單號":"BY202204150031","料號":"H1000-11X","品名":"大刀片鍛件(中碳)無YBICO","數量":"1400","來源廠商":"世鎰","日期":"2022/04/19","下一關":"待發","地區":"加工","行號":"1"},{"單號":"BY202204200002","料號":"CA500H-01","品名":"#CA500黑手柄工具盒組件(無YB有彈簧桿)","數量":"63","來源廠商":"鴻鎰","日期":"2022/04/21","下一關":"B1","地區":"B1-A","行號":"2"},{"單號":"BY202204250054","料號":"P1620-63","品名":"P162小手柄(槌模鍛件)","數量":"798","來源廠商":"晉邑(進溢)","日期":"2022/04/28","下一關":"同偉行","地區":"加工","行號":"4"},{"單號":"MK202008210074","料號":"S2460-16","品名":"3!S246盒蓋","數量":"12","來源廠商":"元貝","日期":"2022/04/29","下一關":"同偉行","地區":"加工","行號":"5"},{"單號":"B1","料號":"CA400H-01","品名":"#CA400黑台架組件焊帶盤心(無YBICO)","數量":"33","來源廠商":"重工","日期":"2020/03/31","下一關":"待發","地區":"B1-B","行號":"5"},{"單號":"BY202204290031","料號":"P3000-36X","品名":"P300刀管毛件(車兩溝小孔)","數量":"12757","來源廠商":"將材","日期":"2022/05/03","下一關":"待發","地區":"待發","行號":"4"},{"單號":"BY202204290039","料號":"T283T0-SP0-A10","品名":"T283灰刀架伸縮抹片黑TPR組件","數量":"238","來源廠商":"王秀燕","日期":"2022/05/03","下一關":"2F","地區":"2F","行號":"2"},{"單號":"BY202204290005","料號":"CA100-48X","品名":"CA100牙管螺母鍛件(多種加工)","數量":"1700","來源廠商":"世鎰","日期":"2022/05/05","下一關":"待發","地區":"加工","行號":"2"},{"單號":"BY202204290005","料號":"CA100-48X","品名":"CA100牙管螺母鍛件(多種加工)","數量":"1700","來源廠商":"世鎰","日期":"2022/05/05","下一關":"待發","地區":"加工","行號":"2"},{"單號":"BY202205040027","料號":"P2400W-16Y","品名":"3!白手柄毛件","數量":"1655","來源廠商":"鴻鎰","日期":"2022/05/09","下一關":"晶幃","地區":"加工","行號":"8"},{"單號":"BY202205040027","料號":"CA240H-09","品名":"#CA240黑手柄鐵管組件(黑亮光)","數量":"130","來源廠商":"鴻鎰","日期":"2022/05/09","下一關":"B14000","地區":"B1-A","行號":"3"},{"單號":"BY202205060041","料號":"YC310-22","品名":"YC310鐵管手柄(鐵)HR30N 66~75","數量":"600","來源廠商":"伍輝","日期":"2022/05/09","下一關":"國榮","地區":"待發","行號":"4"},{"單號":"IO202205050042","料號":"P1170-01X","品名":"P117本台鑄件(YBICO)(ADC-10)","數量":"1350","來源廠商":"億峰富","日期":"2022/05/04","下一關":"待發","地區":"3F","行號":"2"},{"單號":"IO202205050042","料號":"P1170-01X","品名":"P117本台鑄件(YBICO)(ADC-10)","數量":"1350","來源廠商":"億峰富","日期":"2022/05/04","下一關":"待發","地區":"3F","行號":"2"},{"單號":"盤盈 待發","料號":"P5800N-01Y","品名":"P580電鎳鋁本台毛件","數量":"311","來源廠商":"盤盈","日期":"2020/03/31","下一關":"待發","地區":"3F","行號":"2"},{"單號":"盤盈 待發","料號":"BD603-14X","品名":"BD603刀座架鐵管毛件口32*550*T1.5","數量":"100","來源廠商":"盤盈","日期":"2020/03/31","下一關":"待發","地區":"3F","行號":"2"},{"單號":"BY202205090044","料號":"CA180-02","品名":"#CA180黑手柄大工具盒組件(無YBICO)","數量":"11","來源廠商":"山杰","日期":"2022/05/10","下一關":"B1","地區":"B1-D","行號":"4"},{"單號":"BY202204060029","料號":"CA100-23B","品名":"@無縫牙管(254mm)","數量":"101","來源廠商":"勇盛","日期":"2022/04/07","下一關":"待發","地區":"B1-A","行號":"2"},{"單號":"BY202205110013","料號":"CA360H-07","品名":"#(組裝前育仟需先通孔)#CA360黑左側台架組件","數量":"71","來源廠商":"鴻鎰","日期":"2022/05/11","下一關":"B14000","地區":"B1-B","行號":"1"},{"單號":"BY202205110013","料號":"CA360H-04","品名":"#CA360黑右側台架組件","數量":"69","來源廠商":"鴻鎰","日期":"2022/05/11","下一關":"B14000","地區":"B1-B","行號":"2"},{"單號":"BY202205110013","料號":"CA400H-25","品名":"#CA400黑母帶盤組件OD710mm","數量":"120","來源廠商":"鴻鎰","日期":"2022/05/11","下一關":"B14000","地區":"B1-D","行號":"4"},{"單號":"BY202203020004","料號":"BD200-56A","品名":"長方鐵管(上軌道)1763mm","數量":"1","來源廠商":"勇盛","日期":"2022/03/02","下一關":"同偉行","地區":"加工","行號":"8"},{"單號":"BY202205170037","料號":"CA247H-01","品名":"#(用完改CA259H-01)CA247黑台架組件","數量":"25","來源廠商":"山杰","日期":"2022/05/17","下一關":"B1","地區":"B1-B","行號":"1"},{"單號":"B1","料號":"CA660H-09","品名":"#CA660黑手柄工具盒組件","數量":"42","來源廠商":"山杰","日期":"2021/09/08","下一關":"待發","地區":"B1-B","行號":"1"},{"單號":"B1","料號":"CA400H-20","品名":"#CA400黑公帶盤組件OD710mm","數量":"83","來源廠商":"鴻鎰","日期":"2022/03/30","下一關":"B1","地區":"B1-A","行號":"6"},{"單號":"BY202205130009","料號":"T2310-02Y","品名":"T231三角板毛件","數量":"11475","來源廠商":"守宬(展昕)","日期":"2022/05/19","下一關":"待發","地區":"3F","行號":"2"},{"單號":"BY202205160007","料號":"CA540-02","品名":"#CA540手柄工具盒組件無YB(無彈簧桿)","數量":"20","來源廠商":"鴻鎰","日期":"2022/05/19","下一關":"B1","地區":"B1-A","行號":"3"},{"單號":"BY202205230008","料號":"H3050-03B-X","品名":"H305直刀彎鐵管7/8*2.0*395毛件","數量":"1000","來源廠商":"鴻隆慶","日期":"2022/05/23","下一關":"森太","地區":"5F","行號":"2"},{"單號":"BY202205230008","料號":"H3050-03B-X","品名":"H305直刀彎鐵管7/8*2.0*395毛件","數量":"1000","來源廠商":"鴻隆慶","日期":"2022/05/23","下一關":"森太","地區":"5F","行號":"2"},{"單號":"BY202205200018","料號":"PD307-002","品名":"正四角管(立管)口32*1.5*1265mmL","數量":"100","來源廠商":"鴻隆慶","日期":"2022/05/23","下一關":"待發","地區":"5F","行號":"2"},{"單號":"BY202205200038","料號":"CA400H-20","品名":"#CA400黑公帶盤組件OD710mm","數量":"19","來源廠商":"鴻鎰","日期":"2022/05/23","下一關":"B1","地區":"B1-A","行號":"3"},{"單號":"BY202205230028","料號":"S2400-24","品名":"S240小手柄(電鎳)","數量":"407","來源廠商":"金彰","日期":"2022/05/26","下一關":"3F","地區":"3F","行號":"2"},{"單號":"BY202205230028","料號":"S2400-24","品名":"S240小手柄(電鎳)","數量":"1800","來源廠商":"金彰","日期":"2022/05/26","下一關":"3F","地區":"3F","行號":"2"},{"單號":"MK202205240003","料號":"CA503H-01N","品名":"CA503黑手柄工具盒組件(無YB有彈簧桿)NORTHSHORE","數量":"12","來源廠商":"元貝","日期":"2022/05/26","下一關":"B1","地區":"B1-D","行號":"3"},{"單號":"BY202109140026","料號":"CA432H-12","品名":"CA432黑工具箱","數量":"36","來源廠商":"鴻鎰","日期":"2022/05/26","下一關":"B1","地區":"B1-D","行號":"3"},{"單號":"BY202205250023","料號":"CA100-23B","品名":"@無縫牙管(254mm)","數量":"312","來源廠商":"勇盛","日期":"2022/05/27","下一關":"B14000","地區":"B1-A","行號":"2"},{"單號":"BY202205260004","料號":"CA400H-20","品名":"#CA400黑公帶盤組件OD710mm","數量":"60","來源廠商":"鴻鎰","日期":"2022/05/27","下一關":"B14000","地區":"B1-A","行號":"6"},{"單號":"BY202205260004","料號":"CA650H-010","品名":"#黑手柄管大工具盒組件(無YBICO)","數量":"60","來源廠商":"鴻鎰","日期":"2022/05/27","下一關":"B14000","地區":"B1-A","行號":"2"},{"單號":"BY202205250014","料號":"S2961-03","品名":"S296底座(電鎳)(YBICO)無頭螺絲鎖","數量":"1001","來源廠商":"巨岦","日期":"2022/05/27","下一關":"同偉行","地區":"加工","行號":"8"},{"單號":"BY202205310002","料號":"CA920H-01","品名":"#CA920黑工具箱組件(黑平光)","數量":"105","來源廠商":"鴻鎰","日期":"2022/05/31","下一關":"B14000","地區":"B1-A","行號":"2"},{"單號":"BY202205310002","料號":"CA920H-01","品名":"#CA920黑工具箱組件(黑平光)","數量":"54","來源廠商":"鴻鎰","日期":"2022/05/31","下一關":"B14000","地區":"B1-A","行號":"3"},{"單號":"BY202206010023","料號":"CA920H-01","品名":"#CA920黑工具箱組件(黑平光)","數量":"84","來源廠商":"鴻鎰","日期":"2022/06/06","下一關":"B1","地區":"B1-A","行號":"5"},{"單號":"BY202206010023","料號":"CA920H-01","品名":"#CA920黑工具箱組件(黑平光)","數量":"52","來源廠商":"鴻鎰","日期":"2022/06/06","下一關":"B1","地區":"B1-A","行號":"5"},{"單號":"BY202206010023","料號":"CA2481-28","品名":"(用完改CA2481H-24) #鐵盤ID58*495mm單層(有臍)孔12.5mm","數量":"100","來源廠商":"鴻鎰","日期":"2022/06/06","下一關":"B1","地區":"B1-備料","行號":"無"},{"單號":"BY202206010023","料號":"CA2481-29","品名":"#黑鐵盤ID58*495mm單層(有臍)孔15.5mm","數量":"100","來源廠商":"鴻鎰","日期":"2022/06/06","下一關":"B1","地區":"B1-B","行號":"2"},{"單號":"MK202206010010","料號":"PE101-55X","品名":"2!!PE101腳踏鑄件","數量":"351","來源廠商":"元貝","日期":"2022/06/06","下一關":"晶幃","地區":"加工","行號":"4"},{"單號":"MK202206010013","料號":"S2680-01Y","品名":"2!S268活動蓋毛件(打8)","數量":"372","來源廠商":"元貝","日期":"2022/06/07","下一關":"待發","地區":"加工","行號":"2"},{"單號":"MK202101290008","料號":"PD308-058","品名":"PD308刀片架","數量":"43","來源廠商":"元貝","日期":"2022/06/07","下一關":"待發","地區":"5F","行號":"2"},{"單號":"BY202206080018","料號":"CA120Z-47","品名":"#CA120橘(166C)母帶盤OD616mm","數量":"100","來源廠商":"鴻鎰","日期":"2022/06/09","下一關":"B1","地區":"B1-D","行號":"4"},{"單號":"BY202206080018","料號":"CA120Z-51","品名":"#CA120橘(166C)公帶盤組件OD616mm(4小孔)","數量":"100","來源廠商":"鴻鎰","日期":"2022/06/09","下一關":"B1","地區":"B1-D","行號":"4"},{"單號":"BY202206080018","料號":"CA124Z-47","品名":"#橘(166C)母帶盤0D616mm","數量":"45","來源廠商":"鴻鎰","日期":"2022/06/09","下一關":"B1","地區":"B1-A","行號":"6"},{"單號":"BY202206080013","料號":"CA620G-01","品名":"#CA620台架組件(PANTONE 322U)","數量":"159","來源廠商":"鴻鎰","日期":"2022/06/09","下一關":"B14000","地區":"B1-D","行號":"3"},{"單號":"BY202206090005","料號":"T26000-G0-B22","品名":"T260柄綠邊蓋組件","數量":"77","來源廠商":"邱博鴻","日期":"2022/06/09","下一關":"2F","地區":"2F","行號":"2"},{"單號":"BY202206020036","料號":"PE1004-47Y","品名":"1/2壓塊毛件(4140)","數量":"170","來源廠商":"創顯","日期":"2022/06/07","下一關":"待發","地區":"加工","行號":"5"},{"單號":"BY202206090004","料號":"YP370-50Y","品名":"1!!YP370刀心毛件(S45C)","數量":"2170","來源廠商":"里祥","日期":"2022/06/13","下一關":"晶幃","地區":"加工","行號":"6"},{"單號":"BY202206130002","料號":"P1171-12X","品名":"P1171四角阻齒鑄件(S25C)","數量":"5250","來源廠商":"沿峰","日期":"2022/06/15","下一關":"待發","地區":"加工","行號":"2"},{"單號":"BY202206130027","料號":"CA400Y-25","品名":"(依訂單烤漆) #CA400黃母帶盤組件OD710mm","數量":"7","來源廠商":"鴻鎰","日期":"2022/06/15","下一關":"B14000","地區":"B1-A","行號":"4"},{"單號":"BY202206130027","料號":"CA400Y-20","品名":"(依訂單烤漆) CA400黃公帶盤組件OD710mm","數量":"17","來源廠商":"鴻鎰","日期":"2022/06/15","下一關":"B14000","地區":"B1-A","行號":"4"},{"單號":"BY202206160008","料號":"BD200-56A","品名":"長方鐵管(上軌道)1763mm","數量":"400","來源廠商":"勇盛","日期":"2022/06/17","下一關":"同偉行","地區":"加工","行號":"8"},{"單號":"BY202206160012","料號":"P1160G-01Y","品名":"P116綠本台毛件YBICO","數量":"37","來源廠商":"鴻鎰","日期":"2022/06/17","下一關":"同偉行","地區":"加工","行號":"1"},{"單號":"BY202206170015","料號":"AC100-04X","品名":"AC100底座長方管毛件 25*50*T1.5*L500","數量":"298","來源廠商":"鴻隆慶","日期":"2022/06/17","下一關":"待發","地區":"3F","行號":"1"},{"單號":"BY202206170046","料號":"S2980-01B","品名":"S298手柄鐵管(熱處理)","數量":"2000","來源廠商":"伍輝","日期":"2022/06/20","下一關":"森太","地區":"加工","行號":"2"},{"單號":"BY202206220034","料號":"CA7242Z-41","品名":"#CA7242橘公帶盤組件","數量":"82","來源廠商":"鴻鎰","日期":"2022/06/23","下一關":"B1","地區":"B1-B","行號":"2"},{"單號":"BY202206220034","料號":"CA720Z-47","品名":"#橘紅母帶盤400*635mm單層","數量":"60","來源廠商":"鴻鎰","日期":"2022/06/23","下一關":"B1","地區":"B1-B","行號":"1"},{"單號":"BY202206240021","料號":"H1000-11X","品名":"大刀片鍛件(中碳)無YBICO","數量":"1385","來源廠商":"世鎰","日期":"2022/06/27","下一關":"待發","地區":"加工","行號":"2"},{"單號":"BY202206240021","料號":"H1000-11X","品名":"大刀片鍛件(中碳)無YBICO","數量":"539","來源廠商":"世鎰","日期":"2022/06/27","下一關":"待發","地區":"待發","行號":"3"},{"單號":"B1","料號":"CA130-01","品名":"#(用完改CA130H-60)鐵管台架組件(長輪心)","數量":"38","來源廠商":null,"日期":"2021/03/30","下一關":"待發","地區":"B1-A","行號":"5"},{"單號":"BY202206210032","料號":"CA100-03Y","品名":"大孔小工具盒(YBICO)","數量":"262","來源廠商":"靖盈(新濟)","日期":"2022/06/23","下一關":"森太","地區":"B1-C","行號":"5"},{"單號":"BY202206210035","料號":"BD100B-03","品名":"#BD100藍台架立管組件(藍)","數量":"1","來源廠商":"優進(實進)","日期":"2022/06/28","下一關":"待發","地區":"B1-C","行號":"3"},{"單號":"BY202206270035","料號":"T9646G-01","品名":"T9646綠台","數量":"1","來源廠商":"山杰","日期":"2022/06/28","下一關":"同偉行","地區":"加工","行號":"5"},{"單號":"BY202206280016","料號":"T524DM-FL2-B21","品名":"T524藍320C柄紫藍邊蓋鐵接無MIT組件","數量":"200","來源廠商":"柯榮華","日期":"2022/06/28","下一關":"2F","地區":"2F","行號":"2"},{"單號":"MK202205250064","料號":"W1130-03B","品名":"W113 7/8*320*t1.6mm鐵管","數量":"2000","來源廠商":"元貝","日期":"2022/06/30","下一關":"待發","地區":"3F","行號":"1"},{"單號":"BY202206300003","料號":"BD330-03","品名":"#1#BD330轉盤OD900mm","數量":"40","來源廠商":"鴻鎰","日期":"2022/06/30","下一關":"B14000","地區":"B1-C","行號":"2"},{"單號":"BY202206300003","料號":"BD100H-56","品名":"BD100黑軌道架組件(黑平光)","數量":"139","來源廠商":"鴻鎰","日期":"2022/06/30","下一關":"B14000","地區":"B1-C","行號":"3"},{"單號":"MK202204010045","料號":"S2600-11Y","品名":"#S260本台毛件(有YBICO)(槌模)","數量":"620","來源廠商":"元貝","日期":"2022/06/30","下一關":"伍輝","地區":"加工","行號":"1"},{"單號":"MK202204250004","料號":"P2680-02Y","品名":"3!P268本台毛件","數量":"1000","來源廠商":"元貝","日期":"2022/07/01","下一關":"鴻鎰","地區":"B1-C","行號":"2"},{"單號":"BY202207050013","料號":"CA790-01","品名":"#CA790藍台架組件","數量":"70","來源廠商":"山杰","日期":"2022/07/06","下一關":"B14000","地區":"B1-B","行號":"5"},{"單號":"BY202207050013","料號":"CA350-01","品名":"#藍台架組件","數量":"111","來源廠商":"山杰","日期":"2022/07/06","下一關":"B14000","地區":"B1-B","行號":"5"},{"單號":"BY202206240034","料號":"CA200H-51","品名":"#CA200黑公帶盤組件ID200*OD500mm(4小孔","數量":"100","來源廠商":"鴻鎰","日期":"2022/06/29","下一關":"B14000","地區":"B1-A","行號":"4"},{"單號":"B1","料號":"CA750-10","品名":"#藍手柄工具盒組件","數量":"20","來源廠商":"鴻鎰","日期":"2020/03/31","下一關":"待發","地區":"B1-B","行號":"5"},{"單號":"BY202207050020","料號":"CA100H-51","品名":"#CA100黑公帶盤組件ID200*OD610mm(4小孔)","數量":"18","來源廠商":"鴻鎰","日期":"2022/07/07","下一關":"B1","地區":"B1-備料","行號":"無"},{"單號":"B1","料號":"CA720H-47A-P","品名":"#黑母帶盤400*635mm單層(沖ASPECT) 孔29mm","數量":"5","來源廠商":null,"日期":"2022/07/07","下一關":"B1","地區":"B1-B","行號":"1"},{"單號":"BY202204250005","料號":"T2741-11Y","品名":"T2741鐵板毛件(小長方洞)","數量":"3000","來源廠商":"長恆","日期":"2022/04/25","下一關":"待發","地區":"3F","行號":"1"},{"單號":"BY202204250005","料號":"T2741-11Y","品名":"T2741鐵板毛件(小長方洞)","數量":"3000","來源廠商":"長恆","日期":"2022/04/25","下一關":"待發","地區":"3F","行號":"1"},{"單號":"BY202207040030","料號":"LM120-02X","品名":"鋁推桿毛件(AL6063-T5)(一端斜切)與LM100-02X同訂","數量":"566","來源廠商":"高享","日期":"2022/07/06","下一關":"B14000","地區":"B1-A","行號":"1"},{"單號":"BY202207040030","料號":"LM100-02X","品名":"鋁四角推桿毛件FP266(AL6063-T5)與LM120-02X同訂","數量":"63","來源廠商":"高享","日期":"2022/07/06","下一關":"B14000","地區":"B1-A","行號":"1"},{"單號":"BY202207050025","料號":"P1190B-01Y","品名":"P119藍(RAL5005)本台毛件(YBICO)","數量":"535","來源廠商":"晨品富(弘昌)","日期":"2022/07/07","下一關":"同偉行","地區":"加工","行號":"8"},{"單號":"BY202207010024","料號":"T3370-10Y","品名":"T337鐵板毛件(沖7A)","數量":"3149","來源廠商":"百亨隆","日期":"2022/07/06","下一關":"5F4000","地區":"2F","行號":"2"},{"單號":"BY202207010024","料號":"T3370-10Y","品名":"T337鐵板毛件(沖7A)","數量":"3750","來源廠商":"百亨隆","日期":"2022/07/06","下一關":"5F4000","地區":"5F","行號":"1"},{"單號":"BY202207010011","料號":"T3370-10Y","品名":"T337鐵板毛件(沖7A)","數量":"3750","來源廠商":"百亨隆","日期":"2022/07/06","下一關":"5F4000","地區":"5F","行號":"1"},{"單號":"BY202207010011","料號":"T3370-10Y","品名":"T337鐵板毛件(沖7A)","數量":"3750","來源廠商":"百亨隆","日期":"2022/07/06","下一關":"5F4000","地區":"5F","行號":"1"},{"單號":"BY202203240006","料號":"H3000-09A","品名":"1!母連桿","數量":"16","來源廠商":"和峰","日期":"2022/07/11","下一關":"待發","地區":"3F","行號":"2"},{"單號":"66倉","料號":"P1170-01X","品名":"P117本台鑄件(YBICO)(ADC-10)","數量":"2066","來源廠商":"66倉","日期":"2021/04/28","下一關":"待發","地區":"B1-C","行號":"5"},{"單號":"66倉","料號":"P1190-01Y","品名":"(可替換P1170-01Y-)P119本台毛件(YBICO)","數量":"267","來源廠商":"66倉","日期":"2021/02/17","下一關":"待發","地區":"B1-C","行號":"2"},{"單號":"66倉","料號":"P3910-28X","品名":"(用完改訂P1160-28X)P391鋁柄鑄件","數量":"394","來源廠商":"66倉","日期":"2021/01/29","下一關":"待發","地區":"B1-C","行號":"1"},{"單號":"66倉","料號":"P3910-28X","品名":"(用完改訂P1160-28X)P391鋁柄鑄件","數量":"2100","來源廠商":"66倉","日期":"2021/04/22","下一關":"待發","地區":"B1-C","行號":"1"},{"單號":"66倉","料號":"P1170-01X","品名":"P117本台鑄件(YBICO)(ADC-10)","數量":"1242","來源廠商":"66倉","日期":"2021/10/22","下一關":"待發","地區":"B1-C","行號":"2"},{"單號":"BY202206070004","料號":"T3400-04Y","品名":"T340鐵板毛件","數量":"1500","來源廠商":"卯勝","日期":"2022/06/08","下一關":"待發3F","地區":"3F","行號":"2"},{"單號":"BY202206070004","料號":"T3400-04Y","品名":"T340鐵板毛件","數量":"1439","來源廠商":"卯勝","日期":"2022/06/08","下一關":"待發3F","地區":"3F","行號":"2"},{"單號":"B1","料號":"CA650-05","品名":"#CA650黑台架組件","數量":"52","來源廠商":"山杰","日期":"2021/11/25","下一關":"待發","地區":"B1-A","行號":"4"},{"單號":"MK202110050109","料號":"S260X-11Y","品名":"#S260本台毛件(無YBICO)(槌模)","數量":"589","來源廠商":"同偉行","日期":"2022/07/05","下一關":"待發","地區":"加工","行號":"1"},{"單號":"MK202110050109","料號":"S260X-11Y","品名":"#S260本台毛件(無YBICO)(槌模)","數量":"600","來源廠商":"同偉行","日期":"2022/07/15","下一關":"待發","地區":"加工","行號":"1"},{"單號":"BY202207140013","料號":"CA100-23B","品名":"@無縫牙管(254mm)","數量":"1615","來源廠商":"勇盛","日期":"2022/07/18","下一關":"B14000","地區":"B1-A","行號":"1"},{"單號":"BY202207140009","料號":"T2870-01Y","品名":"T287小鐵板毛件(大長方洞)","數量":"3000","來源廠商":"守宬(展昕)","日期":"2022/07/18","下一關":"3F4000","地區":"3F","行號":"1"},{"單號":"BY202207140009","料號":"T2870-01Y","品名":"T287小鐵板毛件(大長方洞)","數量":"3000","來源廠商":"守宬(展昕)","日期":"2022/07/18","下一關":"3F4000","地區":"3F","行號":"1"},{"單號":"BY202207140009","料號":"T2870-01Y","品名":"T287小鐵板毛件(大長方洞)","數量":"3000","來源廠商":"守宬(展昕)","日期":"2022/07/18","下一關":"3F4000","地區":"3F","行號":"1"},{"單號":"BY202207140009","料號":"T2870-01Y","品名":"T287小鐵板毛件(大長方洞)","數量":"3000","來源廠商":"守宬(展昕)","日期":"2022/07/18","下一關":"3F4000","地區":"3F","行號":"1"},{"單號":"BY202207140009","料號":"T2870-01Y","品名":"T287小鐵板毛件(大長方洞)","數量":"3000","來源廠商":"守宬(展昕)","日期":"2022/07/18","下一關":"3F4000","地區":"3F","行號":"1"},{"單號":"待發","料號":"CA7242H-41","品名":"#CA7242黑公帶盤組件","數量":"150","來源廠商":"鴻鎰","日期":"2022/05/11","下一關":"待發","地區":"B1-B","行號":"3"},{"單號":"BY202203280013","料號":"CA6521-05","品名":"#CA6521黑台架組件","數量":"45","來源廠商":"山杰","日期":"2022/03/29","下一關":"山杰","地區":"B1-A","行號":"6"},{"單號":"BY202207150048","料號":"C3180-02","品名":"C318連桿柄","數量":"210","來源廠商":"兆煒","日期":"2022/07/19","下一關":"同偉行","地區":"加工","行號":"6"},{"單號":"BY202207140009","料號":"T2870-01Y","品名":"T287小鐵板毛件(大長方洞)","數量":"3000","來源廠商":"守宬(展昕)","日期":"2022/07/18","下一關":"3F4000","地區":"3F","行號":"1"},{"單號":"BY202207140009","料號":"T2870-01Y","品名":"T287小鐵板毛件(大長方洞)","數量":"3000","來源廠商":"守宬(展昕)","日期":"2022/07/18","下一關":"3F4000","地區":"3F","行號":"1"},{"單號":"BY202207140009","料號":"T2870-01Y","品名":"T287小鐵板毛件(大長方洞)","數量":"1000","來源廠商":"守宬(展昕)","日期":"2022/07/18","下一關":"3F4000","地區":"3F","行號":"1"},{"單號":"BY202207180025","料號":"CA400-12","品名":"CA400工具箱毛件(無YBICO)","數量":"140","來源廠商":"守宬(展昕)","日期":"2022/07/19","下一關":"待發","地區":"B1-C","行號":"2"},{"單號":"BY202207180025","料號":"CA400-12","品名":"CA400工具箱毛件(無YBICO)","數量":"156","來源廠商":"守宬(展昕)","日期":"2022/07/19","下一關":"待發","地區":"B1-C","行號":"2"},{"單號":"BY202207210032","料號":"S2900-12X","品名":"S290花輪毛件(YBICO)","數量":"3128","來源廠商":"將材","日期":"2022/07/22","下一關":"待發","地區":"加工","行號":"2"},{"單號":"BY202207210021","料號":"CA860H-15","品名":"#CA860黑手柄管連工具盒組件","數量":"18","來源廠商":"山杰","日期":"2022/07/25","下一關":"B14000","地區":"B1-A","行號":"2"},{"單號":"BY202207210021","料號":"CA200-24","品名":"#黑母帶盤OD500*ID280雙層","數量":"32","來源廠商":"山杰","日期":"2022/07/25","下一關":"B14000","地區":"B1-A","行號":"5"},{"單號":"BY202207210020","料號":"CA863H-01","品名":"#CA863黑台架組件","數量":"19","來源廠商":"山杰","日期":"2022/07/25","下一關":"B14000","地區":"B1-A","行號":"5"},{"單號":"MK202201280133","料號":"C3160-02Y","品名":"#C316連桿柄毛件","數量":"1030","來源廠商":"同偉行","日期":"2022/07/25","下一關":"晶偉","地區":"加工","行號":"5"},{"單號":"BY202207250024","料號":"CA100-01A","品名":"鐵管架連結板","數量":"1378","來源廠商":"靖盈(新濟)","日期":"2022/07/26","下一關":"待發","地區":"3F","行號":"2"},{"單號":"BY202207150056","料號":"T25100-S0-B21","品名":"T251灰柄無MIT組件","數量":"342","來源廠商":"林芝瑩","日期":"2022/07/18","下一關":"2F","地區":"2F","行號":"7"},{"單號":"BY202207250007","料號":"CA790-01","品名":"#CA790藍台架組件","數量":"21","來源廠商":"山杰","日期":"2022/07/27","下一關":"B14000","地區":"B1-C","行號":"7"},{"單號":"BY202207250030","料號":"CA100-031","品名":"大孔小工具盒(無YBICO)","數量":"247","來源廠商":"靖盈(新濟)","日期":"2022/07/28","下一關":"待發","地區":"委外","行號":"無"},{"單號":"BY202207270028","料號":"H3000-08B-X","品名":"H300手柄鐵管毛件黑皮管3/4*280*T1.5","數量":"1398","來源廠商":"鴻隆慶","日期":"2022/07/29","下一關":"5F4000","地區":"3F","行號":"2"},{"單號":"BY202207270028","料號":"H3050-03B-X","品名":"H305直刀彎鐵管7/8*2.0*395毛件","數量":"1000","來源廠商":"鴻隆慶","日期":"2022/07/29","下一關":"5F4000","地區":"5F","行號":"1"},{"單號":"BY202207270028","料號":"H3050-03B-X","品名":"H305直刀彎鐵管7/8*2.0*395毛件","數量":"1000","來源廠商":"鴻隆慶","日期":"2022/07/29","下一關":"5F4000","地區":"5F","行號":"1"},{"單號":"BY202207270028","料號":"H3050-03B-X","品名":"H305直刀彎鐵管7/8*2.0*395毛件","數量":"1000","來源廠商":"鴻隆慶","日期":"2022/07/29","下一關":"5F4000","地區":"5F","行號":"1"},{"單號":"BY202207270028","料號":"H3050-03B-X","品名":"H305直刀彎鐵管7/8*2.0*395毛件","數量":"1000","來源廠商":"鴻隆慶","日期":"2022/07/29","下一關":"5F4000","地區":"5F","行號":"2"},{"單號":"BY202207270028","料號":"H3050-03B-X","品名":"H305直刀彎鐵管7/8*2.0*395毛件","數量":"1000","來源廠商":"鴻隆慶","日期":"2022/07/29","下一關":"5F4000","地區":"5F","行號":"2"},{"單號":"BY202207270028","料號":"H3050-03B-X","品名":"H305直刀彎鐵管7/8*2.0*395毛件","數量":"1000","來源廠商":"鴻隆慶","日期":"2022/07/29","下一關":"5F4000","地區":"5F","行號":"2"},{"單號":"BY202207270025","料號":"CA720-47","品名":"#黑母帶盤400*635mm單層","數量":"150","來源廠商":"鴻鎰","日期":"2022/07/29","下一關":"B14000","地區":"B1-B","行號":"5"},{"單號":"BY202207270025","料號":"CA720-47","品名":"#黑母帶盤400*635mm單層","數量":"150","來源廠商":"鴻鎰","日期":"2022/07/29","下一關":"B14000","地區":"B1-B","行號":"5"},{"單號":"BY202207270025","料號":"CA540-02","品名":"#CA540手柄工具盒組件無YB(無彈簧桿)","數量":"80","來源廠商":"鴻鎰","日期":"2022/07/29","下一關":"B14000","地區":"B1-C","行號":"7"},{"單號":"BY202207270025","料號":"CA540-02","品名":"#CA540手柄工具盒組件無YB(無彈簧桿)","數量":"80","來源廠商":"鴻鎰","日期":"2022/07/29","下一關":"B14000","地區":"B1-C","行號":"7"},{"單號":"BY202207270004","料號":"CA2532Z-51","品名":"#CA2532橘公帶盤組件OD500mm(2小孔)","數量":"3","來源廠商":"鴻鎰","日期":"2022/07/29","下一關":"B14000","地區":"B1-A","行號":"4"},{"單號":"BY202207270004","料號":"CA2532Z-47","品名":"#CA2532橘(166C)母帶盤OD500mm(2小孔打B)","數量":"1","來源廠商":"鴻鎰","日期":"2022/07/29","下一關":"B14000","地區":"B1-A","行號":"4"},{"單號":"BY202207270004","料號":"CA7242H-41","品名":"#CA7242黑公帶盤組件","數量":"150","來源廠商":"鴻鎰","日期":"2022/07/29","下一關":"B14000","地區":"B1-B","行號":"3"},{"單號":"BY202207270004","料號":"CA100-24","品名":"#黑母帶盤400mm*OD610mm雙層","數量":"150","來源廠商":"鴻鎰","日期":"2022/07/29","下一關":"B14000","地區":"B1-A","行號":"5"},{"單號":"BY202207270004","料號":"CA100H-51","品名":"#CA100黑公帶盤組件ID200*OD610mm(4小孔)","數量":"152","來源廠商":"鴻鎰","日期":"2022/07/29","下一關":"B14000","地區":"B1-A","行號":"5"},{"單號":"BY202207270004","料號":"CA100H-51","品名":"#CA100黑公帶盤組件ID200*OD610mm(4小孔)","數量":"150","來源廠商":"鴻鎰","日期":"2022/07/29","下一關":"B14000","地區":"B1-A","行號":"5"},{"單號":"BY202207290015","料號":"H3050-15","品名":"1!!H305直刀(打2)","數量":"98","來源廠商":"伍輝","日期":"2022/08/01","下一關":"合金","地區":"待發","行號":"3"},{"單號":"MK202207110003","料號":"P2400W-16Y","品名":"3!白手柄毛件","數量":"63","來源廠商":"同偉行","日期":"2022/08/01","下一關":"同偉行","地區":"加工","行號":"8"},{"單號":"MK202203250098","料號":"C3226-11","品名":"手柄鐵管(外雙倒角)","數量":"509","來源廠商":"元貝","日期":"2022/05/25","下一關":"同偉行","地區":"加工","行號":"6"},{"單號":"BY202207270042","料號":"CA540-02","品名":"#CA540手柄工具盒組件無YB(無彈簧桿)","數量":"80","來源廠商":"鴻鎰","日期":"2022/08/01","下一關":"B14000","地區":"B1-D","行號":"3"},{"單號":"BY202207270042","料號":"CA540-02","品名":"#CA540手柄工具盒組件無YB(無彈簧桿)","數量":"46","來源廠商":"鴻鎰","日期":"2022/08/01","下一關":"B14000","地區":"B1-D","行號":"3"},{"單號":"BY202207270042","料號":"BD100H-56","品名":"BD100黑軌道架組件(黑平光)","數量":"71","來源廠商":"鴻鎰","日期":"2022/08/01","下一關":"B14000","地區":"B1-D","行號":"4"},{"單號":"BY202207270049","料號":"CA310H-30","品名":"黑無大孔小工具盒(無YBICO)","數量":"267","來源廠商":"山杰","日期":"2022/08/01","下一關":"B14000","地區":"B1-A","行號":"3"},{"單號":"BY202207270049","料號":"CA700H-61","品名":"#(用完改用CA700H-81) CA700黑台架組件(無焊帶盤心)","數量":"48","來源廠商":"山杰","日期":"2022/08/01","下一關":"B14000","地區":"B1-A","行號":"6"},{"單號":"BY202207270048","料號":"CA180-02","品名":"#CA180黑手柄大工具盒組件(無YBICO)","數量":"97","來源廠商":"山杰","日期":"2022/08/01","下一關":"B14000","地區":"B1-D","行號":"4"},{"單號":"BY202207270048","料號":"CA180-02","品名":"#CA180黑手柄大工具盒組件(無YBICO)","數量":"104","來源廠商":"山杰","日期":"2022/08/01","下一關":"B14000","地區":"B1-D","行號":"4"},{"單號":"BY202207270048","料號":"CA100H-02","品名":"#CA100黑手柄工具盒組件(YBICO)(黑平光)","數量":"144","來源廠商":"山杰","日期":"2022/08/01","下一關":"B14000","地區":"B1-B","行號":"5"},{"單號":"BY202207270048","料號":"CA100H-02","品名":"#CA100黑手柄工具盒組件(YBICO)(黑平光)","數量":"144","來源廠商":"山杰","日期":"2022/08/01","下一關":"B14000","地區":"B1-B","行號":"5"},{"單號":"BY202207280020","料號":"P1620-63X","品名":"P162小手柄(槌模鍛件)","數量":"3800","來源廠商":"世鎰","日期":"2022/08/01","下一關":"翔盛","地區":"待發","行號":"4"},{"單號":"BY202207280021","料號":"P1620-62X","品名":"P162長柄(槌模鍛件)","數量":"1484","來源廠商":"世鎰","日期":"2022/08/01","下一關":"鉅鈦","地區":"待發","行號":"3"},{"單號":"AJ202003310001","料號":"P1080-02X","品名":"1!!P108刀心毛件(57.2mmL)S45C","數量":"2152","來源廠商":"盤盈","日期":"2020/03/31","下一關":"待發","地區":"加工","行號":"1"},{"單號":"BY202208010021","料號":"P1620-63","品名":"P162小手柄(槌模鍛件)","數量":"3061","來源廠商":"晉邑(進溢)","日期":"2022/08/03","下一關":"同偉行","地區":"加工","行號":"4"},{"單號":"BY202208010027","料號":"LM100-02X","品名":"鋁四角推桿毛件FP266(AL6063-T5)與LM120-02X同訂","數量":"939","來源廠商":"高享","日期":"2022/08/03","下一關":"B1待發","地區":"B1-A","行號":"1"},{"單號":"BY202010230063","料號":"PA470-151","品名":"PA470腳踏壓帶本體(原PA475-82-)","數量":"435","來源廠商":"伍輝","日期":"2020/10/23","下一關":"晶幃","地區":"加工","行號":"6"},{"單號":"MK202202080021","料號":"S260X-11Y","品名":"#S260本台毛件(無YBICO)(槌模)","數量":"600","來源廠商":"同偉行","日期":"2022/08/04","下一關":"待發","地區":"加工","行號":"1"},{"單號":"MK202110050109","料號":"S260X-11Y","品名":"#S260本台毛件(無YBICO)(槌模)","數量":"528","來源廠商":"同偉行","日期":"2022/08/04","下一關":"待發","地區":"加工","行號":"1"},{"單號":"BY202208030040","料號":"C3180-02","品名":"C318連桿柄","數量":"910","來源廠商":"兆煒","日期":"2022/08/05","下一關":"待發","地區":"加工","行號":"1"},{"單號":"BY202206220020","料號":"YP370-14","品名":"1!!YP370齒輪","數量":"630","來源廠商":"新錩","日期":"2022/06/23","下一關":"將材","地區":"加工","行號":"2"},{"單號":"B1","料號":"CA650H-010","品名":"#黑手柄管大工具盒組件(無YBICO)","數量":"75","來源廠商":null,"日期":"2022/07/07","下一關":"B1","地區":"B1-A","行號":"3"},{"單號":"B1","料號":"CA270H-09","品名":"黑手柄鐵管組件","數量":"10","來源廠商":"同偉行","日期":"2021/07/13","下一關":"待發","地區":"B1-B","行號":"4"},{"單號":"BY202108040030","料號":"CA276H-52","品名":"#CA276黑母帶盤組件","數量":"26","來源廠商":"鴻鎰","日期":"2022/08/05","下一關":"待發","地區":"B1-B","行號":"2"},{"單號":"BY202110180019","料號":"CA650-51","品名":"外側鐵板(黑色)","數量":"3","來源廠商":"鴻鎰","日期":"2022/08/05","下一關":"B1","地區":"B1-A","行號":"4"},{"單號":"BY202205110013","料號":"CA720H-47A-P","品名":"#黑母帶盤400*635mm單層(沖ASPECT) 孔29mm","數量":"6","來源廠商":"鴻鎰","日期":"2022/08/05","下一關":"B1","地區":"B1-B","行號":"4"},{"單號":"BY202010210038","料號":"CA500H-01A-P","品名":"#CA500黑手柄工具盒組件(ASPECT)","數量":"36","來源廠商":"鴻鎰","日期":"2022/08/05","下一關":"B1","地區":"B1-D","行號":"3"},{"單號":"待發","料號":"CA100-02N","品名":"#CA100黑手柄小工具盒組件NORHT SHORE","數量":"28","來源廠商":null,"日期":"2021/03/30","下一關":"待發","地區":"B1-D","行號":"3"},{"單號":"待發","料號":"CA400H-01","品名":"#CA400黑台架組件焊帶盤心(無YBICO)","數量":"6","來源廠商":null,"日期":"2021/03/30","下一關":"待發","地區":"B1-D","行號":"3"},{"單號":"BY202112060013","料號":"CA322-06","品名":"*(不再訂)(用完用CA324H-06+CA322H-08)#CA322台架組件(無焊帶盤心可穿帶)","數量":"10","來源廠商":"山杰","日期":"2022/08/05","下一關":"B1","地區":"B1-D","行號":"3"},{"單號":"BY202208030038","料號":"S2621-02Y","品名":"S2621刀心毛件(7mm孔)","數量":"6276","來源廠商":"將材","日期":"2022/08/05","下一關":"同偉行","地區":"加工","行號":"5"},{"單號":"BY202208080013","料號":"P1620-63","品名":"P162小手柄(槌模鍛件)","數量":"1389","來源廠商":"晉邑(進溢)","日期":"2022/08/08","下一關":"同偉行","地區":"加工","行號":"4"},{"單號":"BY202208030013","料號":"CA100H-51","品名":"#CA100黑公帶盤組件ID200*OD610mm(4小孔)","數量":"147","來源廠商":"鴻鎰","日期":"2022/08/08","下一關":"B14000","地區":"B1-A","行號":"5"},{"單號":"BY202208030013","料號":"CA500H-01Y","品名":"#CA500黑手柄工具盒組件YBICO(有彈簧桿)","數量":"64","來源廠商":"鴻鎰","日期":"2022/08/08","下一關":"B14000","地區":"B1-B","行號":"3"},{"單號":"IO202205050042","料號":"P1170-01X","品名":"P117本台鑄件(YBICO)(ADC-10)","數量":"1092","來源廠商":"億峰富","日期":"2022/05/04","下一關":"待發","地區":"3F","行號":"2"},{"單號":"BY202203170009","料號":"CA620-21","品名":"底管7/8x1.5x270","數量":"200","來源廠商":"鴻隆慶","日期":"2022/03/18","下一關":"待發","地區":"3F","行號":"2"},{"單號":"BY202208050028","料號":"S2910-07X","品名":"S291齒輪鑄件","數量":"1473","來源廠商":"玖鼎","日期":"2022/08/09","下一關":"待發","地區":"加工","行號":"2"},{"單號":"BY202208050028","料號":"S2470-28X","品名":"S247本台鑄件(脫蠟)YBICO","數量":"50","來源廠商":"玖鼎","日期":"2022/08/09","下一關":"待發","地區":"加工","行號":"5"},{"單號":"BY20210915007","料號":"P2600-02X","品名":"P260本台鑄件(YBICO)","數量":"114","來源廠商":"億峰富","日期":"2021/09/15","下一關":"4000","地區":"待發","行號":"2"},{"單號":"BY202204130016","料號":"H3040-12X","品名":"H304小刀片鍛件(NO YBICO)","數量":"1200","來源廠商":"良璂","日期":"2022/04/14","下一關":"待發","地區":"待發","行號":"3"},{"單號":"BY202208260003","料號":"CA610-06","品名":"鐵管7/8*1.5*300","數量":"500","來源廠商":"鴻隆慶","日期":"2022/08/09","下一關":"3F4000","地區":"3F","行號":"2"},{"單號":"BY202208050007","料號":"AC100-04X","品名":"AC100底座長方管毛件 25*50*T1.5*L500","數量":"2","來源廠商":"鴻隆慶","日期":"2022/08/09","下一關":"3F4000","地區":"3F","行號":"1"},{"單號":"BY202208040025","料號":"CA760H-010","品名":"黑手柄管特大工具盒組件(無YBICO)工具盒底 到柄管底140mm(工具盒在後)","數量":"18","來源廠商":"山杰","日期":"2022/08/05","下一關":"B14000","地區":"B1-C","行號":"7"},{"單號":"BY202208030029","料號":"CA100-24","品名":"#黑母帶盤400mm*OD610mm雙層","數量":"150","來源廠商":"鴻鎰","日期":"2022/08/10","下一關":"B14000","地區":"B1-B","行號":"5"},{"單號":"BY202208030029","料號":"CA100-24","品名":"#黑母帶盤400mm*OD610mm雙層","數量":"91","來源廠商":"鴻鎰","日期":"2022/08/10","下一關":"B14000","地區":"B1-備料","行號":"無"},{"單號":"BY202208100030","料號":"CA244-32","品名":"#CA244黑鐵盤(有臍)ID58*OD310(孔15.5mm)","數量":"13","來源廠商":"鴻鎰","日期":"2022/08/10","下一關":"B1","地區":"B1-A","行號":"3"},{"單號":"BY202208100030","料號":"CA276H-52","品名":"#CA276黑母帶盤組件","數量":"40","來源廠商":"鴻鎰","日期":"2022/08/10","下一關":"B1","地區":"B1-B","行號":"2"},{"單號":"BY202208100030","料號":"CA276H-38","品名":"#CA276黑公帶盤組件","數量":"40","來源廠商":"鴻鎰","日期":"2022/08/10","下一關":"B1","地區":"B1-B","行號":"2"},{"單號":"BY202208090020","料號":"T2741-11Y","品名":"T2741鐵板毛件(小長方洞)","數量":"3000","來源廠商":"長恆","日期":"2022/08/10","下一關":"待發","地區":"3F","行號":"1"},{"單號":"BY202208040001","料號":"T3400-04Y","品名":"T340鐵板毛件","數量":"585","來源廠商":"卯勝","日期":"2022/08/09","下一關":"待發","地區":"5F","行號":"2"},{"單號":"BY202208040001","料號":"T3400-04Y","品名":"T340鐵板毛件","數量":"600","來源廠商":"卯勝","日期":"2022/08/09","下一關":"待發","地區":"5F","行號":"2"},{"單號":"BY202208040001","料號":"T3400-04Y","品名":"T340鐵板毛件","數量":"1500","來源廠商":"卯勝","日期":"2022/08/09","下一關":"待發","地區":"5F","行號":"1"},{"單號":"BY202208040001","料號":"T3400-04Y","品名":"T340鐵板毛件","數量":"1500","來源廠商":"卯勝","日期":"2022/08/09","下一關":"待發","地區":"5F","行號":"1"},{"單號":"BY202208100017","料號":"CA610-04","品名":"CA610中間鐵板條","數量":"1000","來源廠商":"卯勝","日期":"2022/08/10","下一關":"優進","地區":"B1-A","行號":"1"},{"單號":"MK202106180032","料號":"CA851H-10","品名":"#CA851黑手柄工具盒組件","數量":"6","來源廠商":"裝配二組","日期":"2022/08/11","下一關":"B1","地區":"B1-A","行號":"2"},{"單號":"BY202208110018","料號":"CA100-020","品名":"#CA100黑手柄工具盒組件(無YBICO)","數量":"73","來源廠商":"山杰","日期":"2022/08/12","下一關":"B14000","地區":"B1-B","行號":"2"},{"單號":"BY202208110018","料號":"CA100-020","品名":"#CA100黑手柄工具盒組件(無YBICO)","數量":"118","來源廠商":"山杰","日期":"2022/08/12","下一關":"B14000","地區":"B1-B","行號":"3"},{"單號":"BY202208110018","料號":"CA100-020","品名":"#CA100黑手柄工具盒組件(無YBICO)","數量":"161","來源廠商":"山杰","日期":"2022/08/12","下一關":"B14000","地區":"B1-B","行號":"2"},{"單號":"BY202208100055","料號":"CA100H-02A-P","品名":"#CA100黑手柄工具盒組件(ASPECT)","數量":"1","來源廠商":"山杰","日期":"2022/08/12","下一關":"B14000","地區":"B1-A","行號":"2"},{"單號":"BY202208100055","料號":"CA860H-57","品名":"#CA860黑左轉軸架組件","數量":"28","來源廠商":"山杰","日期":"2022/08/12","下一關":"B14000","地區":"B1-B","行號":"1"},{"單號":"BY202208100055","料號":"CA860H-31","品名":"#CA860黑右轉軸架組件","數量":"84","來源廠商":"山杰","日期":"2022/08/12","下一關":"B14000","地區":"B1-B","行號":"1"},{"單號":"BY202208100055","料號":"CA100H-61","品名":"#CA100黑台架組件(無焊帶盤心)","數量":"122","來源廠商":"山杰","日期":"2022/08/12","下一關":"B14000","地區":"B1-備料","行號":"無"},{"單號":"BY202202250055","料號":"CA650H-010","品名":"#黑手柄管大工具盒組件(無YBICO)","數量":"2","來源廠商":"鴻鎰","日期":"2022/08/12","下一關":"B1","地區":"B1-A","行號":"3"},{"單號":"BY202205160007","料號":"CA540-02","品名":"#CA540手柄工具盒組件無YB(無彈簧桿)","數量":"80","來源廠商":null,"日期":"2022/05/19","下一關":"B1","地區":"B1-A","行號":"3"},{"單號":"BY202208110003","料號":"P3100A-01Y","品名":"P310暗紅台毛件(RAL3020)","數量":"2700","來源廠商":"冠承","日期":"2022/08/12","下一關":"同偉行","地區":"加工","行號":"8"},{"單號":"BY202208090020","料號":"T2741-11Y","品名":"T2741鐵板毛件(小長方洞)","數量":"2984","來源廠商":"長恆","日期":"2022/08/10","下一關":"待發","地區":"3F","行號":"1"},{"單號":"BY202208110027","料號":"H3060-07","品名":"H306下刀片","數量":"998","來源廠商":"翔盛","日期":"2022/08/15","下一關":"同偉行","地區":"加工","行號":"6"},{"單號":"BY202208120018","料號":"CA720-47","品名":"#黑母帶盤400*635mm單層","數量":"150","來源廠商":"鴻鎰","日期":"2022/08/15","下一關":"B14000","地區":"B1-B","行號":"3"},{"單號":"BY202208120018","料號":"CA720-47","品名":"#黑母帶盤400*635mm單層","數量":"150","來源廠商":"鴻鎰","日期":"2022/08/15","下一關":"B14000","地區":"B1-B","行號":"3"},{"單號":"BY202208120018","料號":"CA720-47","品名":"#黑母帶盤400*635mm單層","數量":"150","來源廠商":"鴻鎰","日期":"2022/08/15","下一關":"B14000","地區":"B1-B","行號":"3"},{"單號":"BY202208120022","料號":"CA500H-01","品名":"#CA500黑手柄工具盒組件(無YB有彈簧桿)","數量":"64","來源廠商":"鴻鎰","日期":"2022/08/15","下一關":"B14000","地區":"B1-B","行號":"6"},{"單號":"BY202208120022","料號":"CA500H-01","品名":"#CA500黑手柄工具盒組件(無YB有彈簧桿)","數量":"64","來源廠商":"鴻鎰","日期":"2022/08/15","下一關":"B14000","地區":"B1-B","行號":"6"},{"單號":"BY202208120022","料號":"CA500H-01","品名":"#CA500黑手柄工具盒組件(無YB有彈簧桿)","數量":"67","來源廠商":"鴻鎰","日期":"2022/08/15","下一關":"B14000","地區":"B1-B","行號":"6"},{"單號":"BY202208120029","料號":"T52000-S0-A10","品名":"T520灰刀架透明片組件(無YBICO)","數量":"55","來源廠商":"趙美珠","日期":"2022/08/12","下一關":"2F","地區":"2F","行號":"2"},{"單號":"BY202208110013","料號":"BD200-06A","品名":"#ψ1¼*1.8T*1728L 黑皮管","數量":"80","來源廠商":"慶昇","日期":"2022/08/15","下一關":"待發","地區":"B1-C","行號":"4"},{"單號":"BY202208160010","料號":"P3100A-01Y","品名":"P310暗紅台毛件(RAL3020)","數量":"532","來源廠商":"冠承","日期":"2022/08/16","下一關":"同偉行","地區":"加工","行號":"8"},{"單號":"BY202204150045","料號":"T2520-02Y","品名":"3!T252三角板毛件","數量":"16900","來源廠商":"靖盈(新濟)","日期":"2022/08/17","下一關":"待發","地區":"5F","行號":"1"},{"單號":"BY202208170019","料號":"CA320-010","品名":"#(可用CB327H-010)CA320黑手柄工具箱組件無YBICO焊接不同CA100(柄孔10mm)","數量":"50","來源廠商":"山杰","日期":"2022/08/18","下一關":"B14000","地區":"B1-B","行號":"6"},{"單號":"BY202208180018","料號":"CA100-11","品名":"#剎車桿組件(折彎145度)","數量":"2","來源廠商":"鴻鎰","日期":"2022/08/19","下一關":"同偉行","地區":"加工","行號":"6"},{"單號":"BY202208170018","料號":"BD603-06","品名":"#BD603壁掛橫板","數量":"102","來源廠商":"山杰","日期":"2022/08/18","下一關":"B14000","地區":"B1-C","行號":"7"},{"單號":"BY202208170018","料號":"BD100B-70","品名":"#BD100藍台架底管(藍)","數量":"366","來源廠商":"山杰","日期":"2022/08/18","下一關":"B14000","地區":"B1-C","行號":"7"},{"單號":"BY202208180019","料號":"CA500-47","品名":"#CA500黑母帶盤ID400*635mm單層","數量":"14","來源廠商":"鴻鎰","日期":"2022/08/19","下一關":"B14000","地區":"B1-備料","行號":"無"},{"單號":"BY202206080018","料號":"CA124Z-51","品名":"#CA124橘(166C)公帶盤組件OD616mm(4小孔)","數量":"31","來源廠商":"鴻鎰","日期":"2022/06/09","下一關":"B1","地區":"B1-A","行號":"4"},{"單號":"B1","料號":"CA100Y-51","品名":"#CA100黃公帶盤組件ID200*OD610mm(4小孔","數量":"27","來源廠商":"鴻鎰","日期":"2021/11/02","下一關":"待發","地區":"B1-A","行號":"6"},{"單號":"BY202208160032","料號":"CA720-47","品名":"#黑母帶盤400*635mm單層","數量":"150","來源廠商":"鴻鎰","日期":"2022/08/17","下一關":"B14000","地區":"B1-D","行號":"3"},{"單號":"BY202208160032","料號":"CA7242H-41","品名":"#CA7242黑公帶盤組件","數量":"147","來源廠商":"鴻鎰","日期":"2022/08/17","下一關":"B14000","地區":"B1-D","行號":"3"},{"單號":"BY202208160032","料號":"CA720-47","品名":"#黑母帶盤400*635mm單層","數量":"7","來源廠商":"鴻鎰","日期":"2022/08/17","下一關":"B14000","地區":"B1-備料","行號":"無"},{"單號":"BY202208160032","料號":"CA7242H-41","品名":"#CA7242黑公帶盤組件","數量":"150","來源廠商":"鴻鎰","日期":"2022/08/17","下一關":"B14000","地區":"B1-D","行號":"3"},{"單號":"BY202206060019","料號":"BD100B-03","品名":"#BD100藍台架立管組件(藍)","數量":"220","來源廠商":"山杰","日期":"2022/06/08","下一關":"B1","地區":"B1-C","行號":"3"},{"單號":"BY202206300009","料號":"BD330-88","品名":"1!BD330圓管(1+1/4*1620*T1.8)","數量":"50","來源廠商":"慶昇","日期":"2022/07/04","下一關":"B1","地區":"B1-C","行號":"3"},{"單號":"MK202205300012","料號":"BD100-86","品名":"BD100 1+1/4*1210mm圓管組件(有孔)","數量":"10","來源廠商":"同偉行","日期":"2022/08/16","下一關":"2F4000","地區":"B1-C","行號":"4"},{"單號":"BY202204140006","料號":"BD200-47","品名":"壓桿7/8*2*1550mmL (電錏)","數量":"37","來源廠商":"慶昇","日期":"2022/04/18","下一關":"B14000","地區":"B1-C","行號":"4"},{"單號":"BY202207080009","料號":"CA610-19","品名":"塑膠工具盒(HB-1218)","數量":"99","來源廠商":"樹德","日期":"2022/08/12","下一關":"B1","地區":"B1-A","行號":"3"},{"單號":"B1","料號":"CA400H-01","品名":"#CA400黑台架組件焊帶盤心(無YBICO)","數量":"8","來源廠商":null,"日期":"2021/03/30","下一關":"B1","地區":"B1-A","行號":"6"},{"單號":"BY202208190036","料號":"S2720-01X","品名":"活動蓋鑄件","數量":"20","來源廠商":"永山宏","日期":"2022/08/22","下一關":"晶幃","地區":"加工","行號":"5"},{"單號":"BY202207270048","料號":"CA100H-02","品名":"#CA100黑手柄工具盒組件(YBICO)(黑平光)","數量":"96","來源廠商":"山杰","日期":"2022/08/01","下一關":"B14000","地區":"B1-A","行號":"4"},{"單號":"B1","料號":"CA100H-02","品名":"#CA100黑手柄工具盒組件(YBICO)(黑平光)","數量":"34","來源廠商":null,"日期":"2022/07/30","下一關":"B1","地區":"B1-A","行號":"6"},{"單號":"BY202208220037","料號":"CA310H-16","品名":"#(用完改用CA310H-30)黑無大孔小工具盒(無YBICO)","數量":"208","來源廠商":"山杰","日期":"2022/08/23","下一關":"B1","地區":"B1-B","行號":"5"},{"單號":"BY202208220037","料號":"CA310H-16","品名":"#(用完改用CA310H-30)黑無大孔小工具盒(無YBICO)","數量":"216","來源廠商":"山杰","日期":"2022/08/23","下一關":"B1","地區":"B1-B","行號":"5"},{"單號":"BY202208220037","料號":"CA310H-16","品名":"#(用完改用CA310H-30)黑無大孔小工具盒(無YBICO)","數量":"216","來源廠商":"山杰","日期":"2022/08/23","下一關":"B1","地區":"B1-B","行號":"5"},{"單號":"BY202208220037","料號":"CA310H-16","品名":"#(用完改用CA310H-30)黑無大孔小工具盒(無YBICO)","數量":"69","來源廠商":"山杰","日期":"2022/08/23","下一關":"B1","地區":"B1-B","行號":"5"},{"單號":"BY202208220038","料號":"CA501H-08","品名":"#CA501黑台架組件(無焊帶盤心)","數量":"75","來源廠商":"山杰","日期":"2022/08/23","下一關":"B1","地區":"B1-D","行號":"4"},{"單號":"BY202208220038","料號":"CA501H-08","品名":"#CA501黑台架組件(無焊帶盤心)","數量":"75","來源廠商":"山杰","日期":"2022/08/23","下一關":"B1","地區":"B1-D","行號":"3"},{"單號":"BY202208220038","料號":"CA501H-08","品名":"#CA501黑台架組件(無焊帶盤心)","數量":"75","來源廠商":"山杰","日期":"2022/08/23","下一關":"B1","地區":"B1-B","行號":"4"},{"單號":"MK202203240059","料號":"S2600-11Y","品名":"#S260本台毛件(有YBICO)(槌模)","數量":"600","來源廠商":"同偉行","日期":"2022/08/23","下一關":"待發","地區":"待發","行號":"2"},{"單號":"MK202203240059","料號":"S2600-11Y","品名":"#S260本台毛件(有YBICO)(槌模)","數量":"600","來源廠商":"同偉行","日期":"2022/08/23","下一關":"待發","地區":"待發","行號":"2"},{"單號":"MK202203240059","料號":"S2600-11Y","品名":"#S260本台毛件(有YBICO)(槌模)","數量":"600","來源廠商":"同偉行","日期":"2022/08/23","下一關":"待發","地區":"待發","行號":"2"},{"單號":"MK202203240059","料號":"S2600-11Y","品名":"#S260本台毛件(有YBICO)(槌模)","數量":"464","來源廠商":"同偉行","日期":"2022/08/23","下一關":"待發","地區":"待發","行號":"2"},{"單號":"MK202203240059","料號":"S2600-11Y","品名":"#S260本台毛件(有YBICO)(槌模)","數量":"600","來源廠商":"同偉行","日期":"2022/08/23","下一關":"待發","地區":"待發","行號":"2"},{"單號":"MK202203240059","料號":"S2600-11Y","品名":"#S260本台毛件(有YBICO)(槌模)","數量":"600","來源廠商":"同偉行","日期":"2022/08/23","下一關":"待發","地區":"待發","行號":"2"},{"單號":"BY202208220031","料號":"CA276-580","品名":"CA276塑膠工具盒(無YBICO)","數量":"87","來源廠商":"保陞","日期":"2022/08/23","下一關":"B1","地區":"B1-A","行號":"3"},{"單號":"BY202208230015","料號":"T25100-S0-B21","品名":"T251灰柄無MIT組件","數量":"128","來源廠商":"邱博鴻","日期":"2022/08/23","下一關":"2F","地區":"2F","行號":"7"},{"單號":"BY202208220024","料號":"BD100-47","品名":"BD100壓桿7/8*1032L*T2.0","數量":"100","來源廠商":"慶昇","日期":"2022/08/23","下一關":"B1","地區":"B1-C","行號":"4"},{"單號":"BY202208240020","料號":"CA850-45","品名":"10風硬輪","數量":"100","來源廠商":"得貹","日期":"2022/08/25","下一關":"B1","地區":"B1-A","行號":"3"},{"單號":"BY202208240009","料號":"CA276A-07","品名":"#CA276暗紅台架組件","數量":"66","來源廠商":"鴻鎰","日期":"2022/08/25","下一關":"B1","地區":"B1-前棟","行號":"無"},{"單號":"BY202208240022","料號":"S2720-07X","品名":"S272 前阻齒鑄件","數量":"388","來源廠商":"永山宏","日期":"2022/08/25","下一關":"晶幃","地區":"加工","行號":"4"},{"單號":"BY202208240022","料號":"S2720-01X","品名":"活動蓋鑄件","數量":"538","來源廠商":"永山宏","日期":"2022/08/25","下一關":"晶幃","地區":"加工","行號":"4"},{"單號":"BY202208240009","料號":"PD120B-07","品名":"#1PD120B藍支架組件(鐵板藍)","數量":"72","來源廠商":"鴻鎰","日期":"2022/08/25","下一關":"5F料架","地區":"5F","行號":"無"},{"單號":"BY202208230006","料號":"CA100-01A","品名":"鐵管架連結板","數量":"530","來源廠商":"靖盈(新濟)","日期":"2022/08/24","下一關":"3F4000","地區":"3F","行號":"2"},{"單號":"BY202208230006","料號":"T5310-01Y","品名":"T531鐵板毛件(酸洗板)","數量":"2080","來源廠商":"靖盈(新濟)","日期":"2022/08/24","下一關":"3F4000","地區":"3F","行號":"2"},{"單號":"BY202208240003","料號":"T2820-11Y","品名":"T282鐵板毛件(平面有磁鐵洞)有3.7mm孔","數量":"3000","來源廠商":"靖盈(新濟)","日期":"2022/08/25","下一關":"3F4000","地區":"3F","行號":"1"},{"單號":"BY202208240003","料號":"T2820-11Y","品名":"T282鐵板毛件(平面有磁鐵洞)有3.7mm孔","數量":"3000","來源廠商":"靖盈(新濟)","日期":"2022/08/25","下一關":"3F4000","地區":"3F","行號":"1"},{"單號":"BY202208220013","料號":"T2511-01Y","品名":"T2511鐵板毛件(有磁鐵洞)","數量":"2500","來源廠商":"卯勝","日期":"2022/08/23","下一關":"3F4000","地區":"3F","行號":"1"},{"單號":"BY202208250023","料號":"CA540H-02Y","品名":"#CA540黑柄工具盒組件YBICO(無彈簧桿)","數量":"64","來源廠商":"鴻鎰","日期":"2022/08/25","下一關":"B1","地區":"B1-A","行號":"2"},{"單號":"BY202208250023","料號":"CA350H-38","品名":"CA350黑單層鐵盤(抽臍)195*OD495孔12.5mm","數量":"92","來源廠商":"鴻鎰","日期":"2022/08/25","下一關":"B1","地區":"B1-B","行號":"1"},{"單號":"BY202207250007","料號":"PD308-057","品名":"#1PD308灰刀片架組件(銀灰1798)","數量":"227","來源廠商":"山杰","日期":"2022/07/27","下一關":"B14000","地區":"5F","行號":"無"},{"單號":"BY202208250039","料號":"CA620B-01","品名":"#CA620台架組件(藍漆)","數量":"54","來源廠商":"山杰","日期":"2022/08/26","下一關":"B14000","地區":"B1-D","行號":"3"},{"單號":"MK202010120153","料號":"YP370S-09Y","品名":"YP370灰鋁手柄毛件","數量":"1880","來源廠商":"晶幃","日期":"2022/08/29","下一關":"同偉行","地區":"加工","行號":"8"},{"單號":"BY202208290018","料號":"E6280-16","品名":"E628齒輪箱","數量":"100","來源廠商":"侑典有限公司","日期":"2022/08/29","下一關":"同偉行","地區":"加工","行號":"5"},{"單號":"BY202208250049","料號":"CA720-47","品名":"#黑母帶盤400*635mm單層","數量":"5","來源廠商":"鴻鎰","日期":"2022/08/29","下一關":"B1","地區":"B1-D","行號":"3"},{"單號":"BY202208250049","料號":"CA7242H-41","品名":"#CA7242黑公帶盤組件","數量":"3","來源廠商":"鴻鎰","日期":"2022/08/29","下一關":"B1","地區":"B1-D","行號":"3"},{"單號":"BY202208290027","料號":"CP35","品名":"5/8PET帶有齒鐵扣(30mm)YBICO","數量":"6000","來源廠商":"光寅","日期":"2022/08/29","下一關":"5F4000","地區":"5F","行號":"無"},{"單號":"BY202208290027","料號":"CP34","品名":"1/2PET帶有齒鐵扣(30mm)YBICO","數量":"78000","來源廠商":"光寅","日期":"2022/08/29","下一關":"5F4000","地區":"5F","行號":"無"},{"單號":"BY202208290027","料號":"CP35","品名":"5/8PET帶有齒鐵扣(30mm)YBICO","數量":"6000","來源廠商":"光寅","日期":"2022/08/29","下一關":"5F4000","地區":"5F","行號":"無"},{"單號":"BY202208290027","料號":"CP35","品名":"5/8PET帶有齒鐵扣(30mm)YBICO","數量":"6000","來源廠商":"光寅","日期":"2022/08/29","下一關":"5F4000","地區":"5F","行號":"無"},{"單號":"BY202208290013","料號":"H3050-02B-X","品名":"H305連桿直鐵管毛件7/8*405*2.0mm厚","數量":"1000","來源廠商":"鴻隆慶","日期":"2022/08/29","下一關":"5F4000","地區":"5F","行號":"無"},{"單號":"BY202208290013","料號":"H3050-02B-X","品名":"H305連桿直鐵管毛件7/8*405*2.0mm厚","數量":"1000","來源廠商":"鴻隆慶","日期":"2022/08/29","下一關":"5F4000","地區":"5F","行號":"無"},{"單號":"BY202208290013","料號":"H3050-02B-X","品名":"H305連桿直鐵管毛件7/8*405*2.0mm厚","數量":"1000","來源廠商":"鴻隆慶","日期":"2022/08/29","下一關":"5F4000","地區":"5F","行號":"無"},{"單號":"BY202208300004","料號":"T3660-04Y","品名":"T366大GAP鐵板毛件","數量":"450","來源廠商":"卯勝","日期":"2022/08/30","下一關":"待發","地區":"3F","行號":"1"},{"單號":"BY202208300004","料號":"T3660-04Y","品名":"T366大GAP鐵板毛件","數量":"450","來源廠商":"卯勝","日期":"2022/08/30","下一關":"待發","地區":"3F","行號":"1"},{"單號":"BY202208300004","料號":"T3660-04Y","品名":"T366大GAP鐵板毛件","數量":"1127","來源廠商":"卯勝","日期":"2022/08/30","下一關":"待發","地區":"3F","行號":"2"},{"單號":"BY202208300004","料號":"T3660-04Y","品名":"T366大GAP鐵板毛件","數量":"1150","來源廠商":"卯勝","日期":"2022/08/30","下一關":"待發","地區":"3F","行號":"2"},{"單號":"BY202111240020","料號":"CA6501-50","品名":"CA6501台架鐵板","數量":"4","來源廠商":null,"日期":"2021/11/24","下一關":"待發","地區":"B1-A","行號":"1"},{"單號":"BY202107260023","料號":"CA670-07","品名":"手柄鐵管1ψx1103Lx1.8T黑皮","數量":"12","來源廠商":null,"日期":"2021/07/26","下一關":"待發","地區":"B1-A","行號":"1"},{"單號":"BY202208300005","料號":"CA610-05","品名":"CA610底鐵板條","數量":"1000","來源廠商":"卯勝","日期":"2022/08/30","下一關":"B1","地區":"B1-A","行號":"1"},{"單號":"BY202209010024","料號":"CA100H-51","品名":"#CA100黑公帶盤組件ID200*OD610mm(4小孔)","數量":"150","來源廠商":"鴻鎰","日期":"2022/09/02","下一關":"B1","地區":"B1-備料","行號":"5"},{"單號":"BY202209010024","料號":"CA100H-51","品名":"#CA100黑公帶盤組件ID200*OD610mm(4小孔)","數量":"82","來源廠商":"鴻鎰","日期":"2022/09/02","下一關":"B1","地區":"B1-備料","行號":"5"},{"單號":"IO202004140032","料號":"PD300-005","品名":"ㄇ型固定板","數量":"49","來源廠商":"其他入庫","日期":"2020/04/14","下一關":"待發","地區":"加工","行號":"2"},{"單號":"B1","料號":"CA200-24","品名":"#黑母帶盤OD500*ID280雙層","數量":"112","來源廠商":null,"日期":"2022/03/30","下一關":"B1","地區":"B1-B","行號":"2"},{"單號":"BY202209010015","料號":"LM120-02X","品名":"鋁推桿毛件(AL6063-T5)(一端斜切)與LM100-02X同訂","數量":"1031","來源廠商":"高享","日期":"2022/09/02","下一關":"B14000","地區":"B1-A","行號":"3"},{"單號":"BY202209010015","料號":"LM100-02X","品名":"鋁四角推桿毛件FP266(AL6063-T5)與LM120-02X同訂","數量":"637","來源廠商":"高享","日期":"2022/09/02","下一關":"B14000","地區":"B1-A","行號":"3"},{"單號":"BY202209020018","料號":"T520T0-H0-A10","品名":"T520黑刀架透明片黑TPR組件","數量":"600","來源廠商":"陳黃尾春","日期":"2022/09/02","下一關":"2F","地區":"2F","行號":"4"},{"單號":"BY202208240009","料號":"CA276A-01","品名":"#CA276暗紅手柄鐵管組件","數量":"71","來源廠商":"鴻鎰","日期":"2022/08/25","下一關":"B1","地區":"B1-前棟","行號":"無"},{"單號":"BY202209050018","料號":"T52100-S0-A10","品名":"T521灰刀架YBICO組件","數量":"240","來源廠商":"陳黃尾春","日期":"2022/09/05","下一關":"2F","地區":"2F","行號":"2"},{"單號":"BY202209050022","料號":"CB720-01","品名":"#CB720手柄特大工具盒組件(無YBICO)","數量":"40","來源廠商":"山杰","日期":"2022/09/06","下一關":"B1","地區":"B1-B","行號":"2"},{"單號":"BY202209050022","料號":"CB720-01","品名":"#CB720手柄特大工具盒組件(無YBICO)","數量":"26","來源廠商":"山杰","日期":"2022/09/06","下一關":"B1","地區":"B1-B","行號":"2"},{"單號":"BY202209050022","料號":"CA330H-38","品名":"CA330黑鐵盤單層(抽臍)ID58*OD310孔","數量":"310","來源廠商":"山杰","日期":"2022/09/06","下一關":"B1","地區":"B1-A","行號":"2"},{"單號":"BY202209050027","料號":"S2410X-25X","品名":"2!!本台大嘴無YBICO鑄件","數量":"1435","來源廠商":"永山宏","日期":"2022/09/06","下一關":"待發","地區":"待發","行號":"2"},{"單號":"BY202209070016","料號":"BD100-02A","品名":"正四角管40*1255L*2T","數量":"150","來源廠商":"鴻隆慶","日期":"2022/09/08","下一關":"待發","地區":"5F","行號":"無"},{"單號":"MK202208240017","料號":"C3180-02Y","品名":"#C318連桿柄毛件","數量":"1053","來源廠商":"同偉行","日期":"2022/09/08","下一關":"待發","地區":"待發","行號":"4"},{"單號":"BY202203230008","料號":"CA3243-06","品名":"#CA3243黑台架組件(無焊帶盤心)車輪心12.5mm","數量":"5","來源廠商":"山杰","日期":"2022/03/23","下一關":"B1","地區":"B1-D","行號":"3"},{"單號":"MK202209020063","料號":"PQ300H-28Y","品名":"PQ300黑手柄毛件","數量":"33","來源廠商":"同偉行","日期":"2022/09/08","下一關":"待發","地區":"加工","行號":"2"},{"單號":"BY202209080045","料號":"T24200-AS-B22","品名":"T242灰柄暗紅邊蓋組件","數量":"1110","來源廠商":"柯榮華","日期":"2022/09/12","下一關":"2F","地區":"2F","行號":"6"},{"單號":"BY202209080045","料號":"T520D0-AH2-B22","品名":"T520黑紅柄暗紅邊蓋組件(YBICO)MIT","數量":"600","來源廠商":"柯榮華","日期":"2022/09/12","下一關":"2F","地區":"2F","行號":"6"},{"單號":"BY202209120020","料號":"CA100H-40","品名":"牙管喇叭套(PE)","數量":"500","來源廠商":"佑昇","日期":"2022/09/13","下一關":"B14000","地區":"B1-A","行號":"1"},{"單號":"BY202209130006","料號":"CA700H-61","品名":"#(用完改用CA700H-81) CA700黑台架組件(無焊帶盤心)","數量":"70","來源廠商":"山杰","日期":"2022/09/13","下一關":"B1","地區":"B1-B","行號":"4"},{"單號":"BY202209130006","料號":"CA700H-61","品名":"#(用完改用CA700H-81) CA700黑台架組件(無焊帶盤心)","數量":"70","來源廠商":"山杰","日期":"2022/09/13","下一關":"B1","地區":"B1-B","行號":"4"},{"單號":"BY202209130006","料號":"CA700H-61","品名":"#(用完改用CA700H-81) CA700黑台架組件(無焊帶盤心)","數量":"70","來源廠商":"山杰","日期":"2022/09/13","下一關":"B1","地區":"B1-B","行號":"4"},{"單號":"BY202209130006","料號":"CA700H-61","品名":"#(用完改用CA700H-81) CA700黑台架組件(無焊帶盤心)","數量":"10","來源廠商":"山杰","日期":"2022/09/13","下一關":"B1","地區":"B1-備料","行號":"無"},{"單號":"BY202209130006","料號":"CA700H-61","品名":"#(用完改用CA700H-81) CA700黑台架組件(無焊帶盤心)","數量":"70","來源廠商":"山杰","日期":"2022/09/13","下一關":"B1","地區":"B1-A","行號":"4"},{"單號":"BY202209130006","料號":"CA700H-81","品名":"CA700黑台架組件(無焊帶盤心)","數量":"64","來源廠商":"山杰","日期":"2022/09/13","下一關":"B1","地區":"B1-D","行號":"3"},{"單號":"BY202209130012","料號":"CA310H-16A","品名":"#(用完改CA310H-30Y) 黑無大孔小工具盒(YB)352*154*130(黑平光)","數量":"237","來源廠商":"山杰","日期":"2022/09/14","下一關":"B1","地區":"B1-B","行號":"3"},{"單號":"BY202209130012","料號":"CA310H-16A","品名":"#(用完改CA310H-30Y) 黑無大孔小工具盒(YB)352*154*130(黑平光)","數量":"176","來源廠商":"山杰","日期":"2022/09/14","下一關":"B1","地區":"B1-B","行號":"3"},{"單號":"BY202209130012","料號":"CA310H-16A","品名":"#(用完改CA310H-30Y) 黑無大孔小工具盒(YB)352*154*130(黑平光)","數量":"192","來源廠商":"山杰","日期":"2022/09/14","下一關":"B1","地區":"B1-B","行號":"3"},{"單號":"BY202209130012","料號":"CA310H-16A","品名":"#(用完改CA310H-30Y) 黑無大孔小工具盒(YB)352*154*130(黑平光)","數量":"136","來源廠商":"山杰","日期":"2022/09/14","下一關":"B1","地區":"B1-B","行號":"3"},{"單號":"BY202209130012","料號":"CA271H-09","品名":"CA271黑手柄鐵管組件","數量":"53","來源廠商":"山杰","日期":"2022/09/14","下一關":"B1","地區":"B1-D","行號":"3"},{"單號":"BY202209130012","料號":"CA100H-61","品名":"#CA100黑台架組件(無焊帶盤心)","數量":"150","來源廠商":"山杰","日期":"2022/09/14","下一關":"B1","地區":"B1-B","行號":"5"},{"單號":"BY202209140020","料號":"T524DM-FLK-B21","品名":"T524藍320C柄紫藍邊蓋鐵接印白Tel:886.566.2457","數量":"1200","來源廠商":"柯榮華","日期":"2022/09/14","下一關":"2F","地區":"2F","行號":"3"},{"單號":"MK202203090114","料號":"SL200-79Y","品名":"黑捲心柄毛件(黑陽極))","數量":"98","來源廠商":"晶幃","日期":"2022/09/15","下一關":"同偉行","地區":"加工","行號":"5"},{"單號":"MK202203100042","料號":"S2720-07","品名":"S272 前阻齒","數量":"500","來源廠商":"同偉行","日期":"2022/09/15","下一關":"國榮","地區":"委外","行號":"無"},{"單號":"BY202209140027","料號":"CA245H-01","品名":"#CA245黑台架組件","數量":"4","來源廠商":"山杰","日期":"2022/09/15","下一關":"B14000","地區":"B1-A","行號":"2"},{"單號":"BY202209140027","料號":"CA245H-01","品名":"#CA245黑台架組件","數量":"136","來源廠商":"山杰","日期":"2022/09/15","下一關":"B14000","地區":"B1-D","行號":"3"},{"單號":"BY202209160032","料號":"WA3500-W","品名":"白 WA350切刀","數量":"100","來源廠商":"黃秀滿","日期":"2022/09/19","下一關":"2F","地區":"2F","行號":"2"},{"單號":"BY202209190014","料號":"CA7242H-41","品名":"#CA7242黑公帶盤組件","數量":"150","來源廠商":"鴻鎰","日期":"2022/09/19","下一關":"B14000","地區":"B1-備料","行號":"無"},{"單號":"BY202209190014","料號":"CA7242H-41","品名":"#CA7242黑公帶盤組件","數量":"44","來源廠商":"鴻鎰","日期":"2022/09/19","下一關":"B14000","地區":"B1-備料","行號":"無"},{"單號":"BY202204290038","料號":"SA106-069-X","品名":"1!!切刀脫蠟鑄件(SKD11)","數量":"245","來源廠商":"永山宏","日期":"2022/05/04","下一關":"同偉行","地區":"加工","行號":"4"},{"單號":"BY202209160023","料號":"C3173-08","品名":"C3173橫刀","數量":"543","來源廠商":"伍輝","日期":"2022/09/19","下一關":"同偉行","地區":"加工","行號":"4"},{"單號":"BY202209160029","料號":"PE102-42X","品名":"PE102凸輪柄鑄件(4140)","數量":"635","來源廠商":"永山宏","日期":"2022/09/20","下一關":"待發","地區":"加工","行號":"1"},{"單號":"BY202209200014","料號":"P1620-01Y","品名":"P162單件底座毛件(鋅4#)","數量":"600","來源廠商":"靖盈(新濟)","日期":"2022/09/20","下一關":"待發","地區":"B1-C","行號":"1"},{"單號":"BY202209200014","料號":"P1620-01Y","品名":"P162單件底座毛件(鋅4#)","數量":"720","來源廠商":"靖盈(新濟)","日期":"2022/09/20","下一關":"待發","地區":"B1-C","行號":"1"},{"單號":"BY202209200014","料號":"P1620-01Y","品名":"P162單件底座毛件(鋅4#)","數量":"600","來源廠商":"靖盈(新濟)","日期":"2022/09/20","下一關":"待發","地區":"B1-C","行號":"1"},{"單號":"BY202209160004","料號":"CA610-02","品名":"CA610長鐵板條","數量":"500","來源廠商":"卯勝","日期":"2022/09/20","下一關":"待發","地區":"B1-A","行號":"1"},{"單號":"BY202209160004","料號":"CA610-02","品名":"CA610長鐵板條","數量":"500","來源廠商":"卯勝","日期":"2022/09/20","下一關":"待發","地區":"B1-A","行號":"1"},{"單號":"BY202209160004","料號":"CA610-03","品名":"CA610左側鐵板條","數量":"500","來源廠商":"卯勝","日期":"2022/09/20","下一關":"待發","地區":"B1-A","行號":"1"},{"單號":"BY202209160004","料號":"CA610-03","品名":"CA610左側鐵板條","數量":"500","來源廠商":"卯勝","日期":"2022/09/20","下一關":"待發","地區":"B1-A","行號":"1"},{"單號":"IO202205310016","料號":"CA610-02","品名":"CA610長鐵板條","數量":"500","來源廠商":"卯勝(超交)","日期":"2022/09/20","下一關":"待發","地區":"B1-A","行號":"1"},{"單號":"IO202205310016","料號":"CA610-02","品名":"CA610長鐵板條","數量":"500","來源廠商":"卯勝(超交)","日期":"2022/09/20","下一關":"待發","地區":"B1-A","行號":"1"},{"單號":"IO202205310016","料號":"CA610-03","品名":"CA610左側鐵板條","數量":"500","來源廠商":"卯勝(超交)","日期":"2022/09/20","下一關":"待發","地區":"B1-A","行號":"1"},{"單號":"IO202205310016","料號":"CA610-03","品名":"CA610左側鐵板條","數量":"500","來源廠商":"卯勝(超交)","日期":"2022/09/20","下一關":"待發","地區":"B1-A","行號":"1"},{"單號":"IO202205310016","料號":"CA610-05","品名":"CA610底鐵板條","數量":"500","來源廠商":"卯勝(超交)","日期":"2022/09/20","下一關":"待發","地區":"B1-A","行號":"1"},{"單號":"IO202205310016","料號":"CA610-05","品名":"CA610底鐵板條","數量":"500","來源廠商":"卯勝(超交)","日期":"2022/09/20","下一關":"待發","地區":"B1-A","行號":"1"},{"單號":"IO202205310016","料號":"CA610-04","品名":"CA610中間鐵板條","數量":"380","來源廠商":"卯勝(超交)","日期":"2022/09/20","下一關":"待發","地區":"B1-A","行號":"1"},{"單號":"IO202205310016","料號":"CA610-04","品名":"CA610中間鐵板條","數量":"500","來源廠商":"卯勝(超交)","日期":"2022/09/20","下一關":"待發","地區":"B1-A","行號":"1"},{"單號":"IO202205310016","料號":"CA610-04","品名":"CA610中間鐵板條","數量":"500","來源廠商":"卯勝(超交)","日期":"2022/09/20","下一關":"待發","地區":"B1-A","行號":"1"},{"單號":"BY202209220001","料號":"H2300-12X","品名":"1!!H230小刀片鍛件(YBICO)","數量":"1200","來源廠商":"鐵益(鐵皇)","日期":"2022/09/22","下一關":"待發","地區":"待發","行號":"4"},{"單號":"BY202209220001","料號":"H2300-12X","品名":"1!!H230小刀片鍛件(YBICO)","數量":"1200","來源廠商":"鐵益(鐵皇)","日期":"2022/09/22","下一關":"待發","地區":"待發","行號":"4"},{"單號":"BY202209220001","料號":"H2300-12X","品名":"1!!H230小刀片鍛件(YBICO)","數量":"1200","來源廠商":"鐵益(鐵皇)","日期":"2022/09/22","下一關":"待發","地區":"待發","行號":"4"},{"單號":"BY202209220001","料號":"H2300-12X","品名":"1!!H230小刀片鍛件(YBICO)","數量":"1196","來源廠商":"鐵益(鐵皇)","日期":"2022/09/22","下一關":"待發","地區":"待發","行號":"4"},{"單號":"BY202209220001","料號":"H2300-12X","品名":"1!!H230小刀片鍛件(YBICO)","數量":"1500","來源廠商":"鐵益(鐵皇)","日期":"2022/09/22","下一關":"待發","地區":"待發","行號":"4"},{"單號":"BY202209230015","料號":"S2900-04Y","品名":"S290手柄鳥毛件(永山宏鑄件代加工)","數量":"2000","來源廠商":"永山宏","日期":"2022/09/26","下一關":"待發","地區":"待發","行號":"4"},{"單號":"BY202209200015","料號":"CA760-02","品名":"(可用CA760-52)特大工具盒毛件(450*220*130)","數量":"149","來源廠商":"靖盈(新濟)","日期":"2022/09/20","下一關":"待發","地區":"B1-C","行號":"1"},{"單號":"BY202209200015","料號":"CA760-02","品名":"(可用CA760-52)特大工具盒毛件(450*220*130)","數量":"150","來源廠商":"靖盈(新濟)","日期":"2022/09/20","下一關":"待發","地區":"B1-C","行號":"1"},{"單號":"BY202209270021","料號":"H3050-15","品名":"1!!H305直刀(打2)","數量":"158","來源廠商":"伍輝","日期":"2022/09/27","下一關":"合金","地區":"待發","行號":"3"},{"單號":"BY202209220023","料號":"PA470-054-X","品名":"汽缸外殼毛件(6061+T6) (原PA475-139-X)","數量":"25","來源廠商":"宏裕","日期":"2022/09/23","下一關":"待發","地區":"待發","行號":"無"},{"單號":"BY202209220023","料號":"PA470-072-X","品名":"進氣本體料件(6061+T6)(原PA475-142-X)","數量":"25","來源廠商":"宏裕","日期":"2022/09/23","下一關":"待發","地區":"待發","行號":"無"},{"單號":"BY202209220023","料號":"PA470-077-X","品名":"外殼連接環毛件(6061+T6)(原PA475-140-X)","數量":"25","來源廠商":"宏裕","日期":"2022/09/23","下一關":"待發","地區":"待發","行號":"無"},{"單號":"mk202206180010","料號":"H2300-11Y","品名":"1!!H230大刀片毛件(無YBICO)","數量":"1089","來源廠商":"生鏽","日期":"2022/06/18","下一關":"待處理","地區":"待發","行號":"1"},{"單號":"BY202209270017","料號":"PD300-002","品名":"PD300正四角管(立管)口32*1.5*732mmL","數量":"200","來源廠商":"鴻隆慶","日期":"2022/09/28","下一關":"優進","地區":"委外","行號":"無"},{"單號":"IO202209290017","料號":"P1190-01Y","品名":"(可替換P1170-01Y-)P119本台毛件(YBICO)","數量":"3","來源廠商":"試磨","日期":"2022/09/29","下一關":"待發","地區":"B1-C","行號":"2"},{"單號":"IO202205310016","料號":"P1160-28X","品名":"P116鋁柄鑄件","數量":"6","來源廠商":"樣品","日期":"2022/09/21","下一關":"待發","地區":"B1-C","行號":"2"},{"單號":"IO202209290017","料號":"P2600-02X","品名":"P260本台鑄件(YBICO)","數量":"4","來源廠商":"試磨","日期":"2022/09/29","下一關":"待發","地區":"B1-C","行號":"5"},{"單號":"66","料號":"P2600-02X","品名":"P260本台鑄件(YBICO)","數量":"2720","來源廠商":"66倉","日期":"2021/01/08","下一關":"待發 ","地區":"B1-C","行號":"5"},{"單號":"66","料號":"P2600-02X","品名":"P260本台鑄件(YBICO)","數量":"2176","來源廠商":"66倉","日期":"2021/01/08","下一關":"待發 ","地區":"B1-C","行號":"5"},{"單號":"BY202209270002","料號":"H1000-11X","品名":"大刀片鍛件(中碳)無YBICO","數量":"1312","來源廠商":"世鎰","日期":"2022/09/29","下一關":"待發 4000","地區":"加工","行號":"2"},{"單號":"BY202209270002","料號":"H1000-11X","品名":"大刀片鍛件(中碳)無YBICO","數量":"1307","來源廠商":"世鎰","日期":"2022/09/29","下一關":"待發 4000","地區":"加工","行號":"3"},{"單號":"BY202209270002","料號":"H1000-11X","品名":"大刀片鍛件(中碳)無YBICO","數量":"1300","來源廠商":"世鎰","日期":"2022/09/29","下一關":"待發 4000","地區":"加工","行號":"2"},{"單號":"BY202209270002","料號":"H1000-11X","品名":"大刀片鍛件(中碳)無YBICO","數量":"1281","來源廠商":"世鎰","日期":"2022/09/29","下一關":"待發 4000","地區":"加工","行號":"2"},{"單號":"BY202209270002","料號":"H1000-11X","品名":"大刀片鍛件(中碳)無YBICO","數量":"1300","來源廠商":"世鎰","日期":"2022/09/29","下一關":"待發 4000","地區":"加工","行號":"2"},{"單號":"MK202206280004","料號":"H2110-12","品名":"1!!H211小刀片(YBICO)","數量":"46","來源廠商":"同偉行","日期":"2022/09/30","下一關":"同偉行","地區":"加工","行號":"6"},{"單號":"BY202209290047","料號":"CA540H-02Y","品名":"#CA540黑柄工具盒組件YBICO(無彈簧桿)","數量":"80","來源廠商":"鴻鎰","日期":"2022/09/30","下一關":"B14000","地區":"B1-A","行號":"3"},{"單號":"BY202209290047","料號":"CA540H-02Y","品名":"#CA540黑柄工具盒組件YBICO(無彈簧桿)","數量":"6","來源廠商":"鴻鎰","日期":"2022/09/30","下一關":"B14000","地區":"B1-A","行號":"3"},{"單號":"BY202209220016","料號":"T287DM-SH-B21","品名":"T287 無商標灰黑柄灰邊蓋鐵接無MIT組件","數量":"600","來源廠商":"柯榮華","日期":"2022/09/22","下一關":"2F","地區":"2F","行號":"3"},{"單號":"BY202210020001","料號":"C3180-09Y","品名":"3!C318鳥毛件","數量":"1420","來源廠商":"有宏","日期":"2022/10/03","下一關":"晶幃","地區":"加工","行號":"6"},{"單號":"BY202209300007","料號":"S2920-03","品名":"S292底座(電鎳)","數量":"24","來源廠商":"金彰","日期":"2022/10/03","下一關":"同偉行","地區":"加工","行號":"8"},{"單號":"BY202209290016","料號":"P4720L-01Y","品名":"3!P472藍RAL5010台毛件(P1N孔)(YBICO)","數量":"8","來源廠商":"瑛鋁","日期":"2022/10/04","下一關":"同偉行","地區":"加工","行號":"8"},{"單號":"MK202209260015","料號":"H1000-11","品名":"H100大刀片(無YBICO)(槌模)","數量":"51","來源廠商":"同偉行","日期":"2022/10/03","下一關":"有宏","地區":"委外","行號":"無"},{"單號":"MK202209160009","料號":"H1010-01","品名":"H101大刀片","數量":"21","來源廠商":"同偉行","日期":"2022/10/03","下一關":"有宏","地區":"委外","行號":"無"},{"單號":"MK202109060012","料號":"S2110-18Y","品名":"#S211本台毛件","數量":"1561","來源廠商":"同偉行","日期":"2022/10/05","下一關":"待發","地區":"加工","行號":"6"},{"單號":"TRL20220224001","料號":"SL201-38X","品名":"SL201鋁本台鑄件(A356+T6)","數量":"397","來源廠商":"台灣恱盛","日期":"2022/02/24","下一關":"晶幃","地區":"加工","行號":"6"},{"單號":"BY202209290015","料號":"P4820-01X","品名":"P482台鑄件(2)YBICO","數量":"335","來源廠商":"瑛鋁","日期":"2022/09/30","下一關":"待發","地區":"B1-C","行號":"1"},{"單號":"BY202209290015","料號":"P4820-01X","品名":"P482台鑄件(2)YBICO","數量":"680","來源廠商":"瑛鋁","日期":"2022/09/30","下一關":"待發","地區":"B1-C","行號":"1"},{"單號":"BY202208220036","料號":"CA240-27","品名":"黑外塑膠帶盤195*OD495mm","數量":"20","來源廠商":"辰鑫","日期":"2022/08/23","下一關":"B1","地區":"B1-C","行號":"7"},{"單號":"BY202208220036","料號":"CA240-27","品名":"黑外塑膠帶盤195*OD495mm","數量":"50","來源廠商":"辰鑫","日期":"2022/08/23","下一關":"B1","地區":"B1-C","行號":"7"},{"單號":"BY202208220036","料號":"CA240-25","品名":"黑內塑膠帶盤195*OD495mm","數量":"59","來源廠商":"辰鑫","日期":"2022/08/23","下一關":"B1","地區":"B1-C","行號":"7"},{"單號":"MK202207270071","料號":"H2110-12Y","品名":"1!!H2110小刀片毛件(YBICO)","數量":"500","來源廠商":"同偉行","日期":"2022/10/05","下一關":"有宏","地區":"待發","行號":"2"},{"單號":"2022-09-14","料號":"CA700H-81","品名":"CA700黑台架組件(無焊帶盤心)","數量":"70","來源廠商":"山杰","日期":"2022/09/14","下一關":"B1","地區":"B1-B","行號":"5"},{"單號":"BY202209140010","料號":"CA700H-81","品名":"CA700黑台架組件(無焊帶盤心)","數量":"74","來源廠商":"山杰","日期":"2022/09/14","下一關":"B1","地區":"B1-B","行號":"5"},{"單號":"BY202209140010","料號":"CA700H-81","品名":"CA700黑台架組件(無焊帶盤心)","數量":"70","來源廠商":"山杰","日期":"2022/09/14","下一關":"B1","地區":"B1-B","行號":"5"},{"單號":"BY202209140010","料號":"CA700H-81","品名":"CA700黑台架組件(無焊帶盤心)","數量":"70","來源廠商":"山杰","日期":"2022/09/14","下一關":"B1","地區":"B1-B","行號":"5"},{"單號":"BY202209140010","料號":"CA700H-81","品名":"CA700黑台架組件(無焊帶盤心)","數量":"70","來源廠商":"山杰","日期":"2022/09/14","下一關":"B1","地區":"B1-B","行號":"5"},{"單號":"BY202210050014","料號":"S2910-08X","品名":"合蓋鑄件","數量":"3028","來源廠商":"鑫立","日期":"2022/10/06","下一關":"待發","地區":"BA","行號":"無"},{"單號":"BY202210030045","料號":"CA245H-01","品名":"#CA245黑台架組件","數量":"84","來源廠商":"山杰","日期":"2022/10/05","下一關":"B14000","地區":"B1-A","行號":"2"},{"單號":"BY202107070014","料號":"PD410-23","品名":"#(用完共用PD410-20) PD410黑台架固定管組件","數量":"97","來源廠商":"鴻鎰","日期":"2022/09/29","下一關":"待發","地區":"B1-C","行號":"7"},{"單號":"BY202210050023","料號":"P1620-63","品名":"P162小手柄(槌模鍛件)","數量":"1","來源廠商":"晉邑(進溢)","日期":"2022/10/07","下一關":"待發","地區":"加工","行號":"4"},{"單號":"BY202209130007","料號":"P3000-36","品名":"P300刀管(睿鼎)車雙溝小孔","數量":"444","來源廠商":"睿鼎","日期":"2022/09/13","下一關":"九井","地區":"待發","行號":"2"},{"單號":"BY202210070013","料號":"T28200-AS-B22","品名":"T282灰柄暗紅邊蓋組件","數量":"165","來源廠商":"柯榮華","日期":"2022/10/07","下一關":"2F","地區":"2F","行號":"5"},{"單號":"BY202210060017","料號":"S2900-03Y","品名":"#3本台毛件(無YBICO)","數量":"184","來源廠商":"錩盛","日期":"2022/10/06","下一關":"同偉行","地區":"加工","行號":"6"},{"單號":"BY202210070012","料號":"CA872H-02","品名":"#CA872黑台架組件","數量":"19","來源廠商":"山杰","日期":"2022/10/11","下一關":"B14000","地區":"B1-C","行號":"7"},{"單號":"BY202209300039","料號":"T287DM-FL2-B21","品名":"T287藍320C柄紫藍邊蓋鐵接無MIT","數量":"648","來源廠商":"柯榮華","日期":"2022/10/03","下一關":"2F","地區":"2F","行號":"2"},{"單號":"BY202210070027","料號":"CA245H-01","品名":"#CA245黑台架組件","數量":"80","來源廠商":"山杰","日期":"2022/10/11","下一關":"B14000","地區":"B1-A","行號":"6"},{"單號":"BY202210070007","料號":"S2420-25X","品名":"S242本台大嘴鑄件(有YBICO)","數量":"500","來源廠商":"岠燁","日期":"2022/10/11","下一關":"待發","地區":"加工","行號":"1"},{"單號":"BY202210070007","料號":"S2420-25X","品名":"S242本台大嘴鑄件(有YBICO)","數量":"500","來源廠商":"岠燁","日期":"2022/10/11","下一關":"待發","地區":"加工","行號":"1"},{"單號":"BY202210070007","料號":"S2420-25X","品名":"S242本台大嘴鑄件(有YBICO)","數量":"500","來源廠商":"岠燁","日期":"2022/10/11","下一關":"待發","地區":"加工","行號":"1"},{"單號":"BY202210070007","料號":"S2420-25X","品名":"S242本台大嘴鑄件(有YBICO)","數量":"500","來源廠商":"岠燁","日期":"2022/10/11","下一關":"待發","地區":"加工","行號":"1"},{"單號":"BY202210070007","料號":"S2420-25X","品名":"S242本台大嘴鑄件(有YBICO)","數量":"224","來源廠商":"岠燁","日期":"2022/10/11","下一關":"待發","地區":"加工","行號":"1"},{"單號":"AJ202003310001","料號":"S2430-13A","品名":"S243大手柄頭","數量":"41","來源廠商":"盤盈","日期":"2020/03/31","下一關":"待發","地區":"加工","行號":"1"},{"單號":"AJ202003310001","料號":"P5800-63","品名":"1!!P580四角阻齒(SKD)","數量":"50","來源廠商":"盤盈","日期":"2020/03/31","下一關":"待發","地區":"加工","行號":"1"},{"單號":"AJ202003310001","料號":"P1630-40Y","品名":"P163小手柄毛件(FCD45)","數量":"20","來源廠商":"盤盈","日期":"2020/03/31","下一關":"待發","地區":"加工","行號":"1"},{"單號":"AJ202003310001","料號":"PQ300-28X","品名":"手柄鑄件","數量":"30","來源廠商":"盤盈","日期":"2020/03/31","下一關":"待發","地區":"加工","行號":"1"},{"單號":"BY202210120002","料號":"CA240-25","品名":"黑內塑膠帶盤195*OD495mm","數量":"60","來源廠商":"辰鑫","日期":"2022/10/12","下一關":"B1","地區":"B1-備料","行號":"1"},{"單號":"BY202210120002","料號":"CA240-25","品名":"黑內塑膠帶盤195*OD495mm","數量":"60","來源廠商":"辰鑫","日期":"2022/10/12","下一關":"B1","地區":"B1-備料","行號":"1"},{"單號":"BY202210120002","料號":"CA240-25","品名":"黑內塑膠帶盤195*OD495mm","數量":"60","來源廠商":"辰鑫","日期":"2022/10/12","下一關":"B1","地區":"B1-備料","行號":"1"},{"單號":"BY202210120002","料號":"CA240-25","品名":"黑內塑膠帶盤195*OD495mm","數量":"60","來源廠商":"辰鑫","日期":"2022/10/12","下一關":"B1","地區":"B1-備料","行號":"1"},{"單號":"BY202210120002","料號":"CA240-25","品名":"黑內塑膠帶盤195*OD495mm","數量":"10","來源廠商":"辰鑫","日期":"2022/10/12","下一關":"B1","地區":"B1-備料","行號":"1"},{"單號":"TRL20220815026","料號":"S3100-01Y","品名":"3!S310本台毛件","數量":"94","來源廠商":"翔盛","日期":"2022/08/15","下一關":"晶幃","地區":"加工","行號":"6"},{"單號":"BY202210120009","料號":"T52000-DS-B22","品名":"T520灰柄紫藍邊蓋組件","數量":"740","來源廠商":"柯榮華","日期":"2022/10/12","下一關":"2F","地區":"2F","行號":"6"},{"單號":"BY202210110017","料號":"T28200-DS-B22","品名":"T282灰柄紫藍邊蓋組件","數量":"97","來源廠商":"柯榮華","日期":"2022/10/11","下一關":"2F","地區":"2F","行號":"3"},{"單號":"BY202101110018","料號":"YP370-11X","品名":"1!!YP370腳踏鑄件","數量":"1144","來源廠商":"沿峰","日期":"2021/01/11","下一關":"晶幃","地區":"加工","行號":"6"},{"單號":"BY202210130001","料號":"CA240-27","品名":"黑外塑膠帶盤195*OD495mm","數量":"10","來源廠商":"辰鑫","日期":"2022/10/13","下一關":"B1","地區":"B1-備料","行號":"2"},{"單號":"BY202210130001","料號":"CA240-27","品名":"黑外塑膠帶盤195*OD495mm","數量":"100","來源廠商":"辰鑫","日期":"2022/10/13","下一關":"B1","地區":"B1-備料","行號":"2"},{"單號":"BY202210130001","料號":"CA240-27","品名":"黑外塑膠帶盤195*OD495mm","數量":"100","來源廠商":"辰鑫","日期":"2022/10/13","下一關":"B1","地區":"B1-備料","行號":"2"},{"單號":"BY202210130001","料號":"CA240-27","品名":"黑外塑膠帶盤195*OD495mm","數量":"100","來源廠商":"辰鑫","日期":"2022/10/13","下一關":"B1","地區":"B1-備料","行號":"2"},{"單號":"BY202210120006","料號":"T5600-04Y","品名":"T560大GAP鐵板毛件(3)","數量":"811","來源廠商":"卯勝","日期":"2022/10/13","下一關":"待發","地區":"3F","行號":"2"},{"單號":"BY202210120035","料號":"CA100-24","品名":"#黑母帶盤400mm*OD610mm雙層","數量":"125","來源廠商":"鴻鎰","日期":"2022/10/13","下一關":"B14000","地區":"B1-備料","行號":"無"},{"單號":"BY202210120035","料號":"CA100-24","品名":"#黑母帶盤400mm*OD610mm雙層","數量":"100","來源廠商":"鴻鎰","日期":"2022/10/13","下一關":"B14000","地區":"B1-備料","行號":"無"},{"單號":"BY202210120035","料號":"S2110-18","品名":"2!S211本台","數量":"250","來源廠商":"鴻鎰","日期":"2022/10/13","下一關":"同偉行","地區":"加工","行號":"5"},{"單號":"BY202210120035","料號":"S2110-18","品名":"2!S211本台","數量":"250","來源廠商":"鴻鎰","日期":"2022/10/13","下一關":"同偉行","地區":"加工","行號":"5"},{"單號":"BY202210120020","料號":"SL201-17","品名":"2!(與SL200-17同)SL201刀座(打B-晶幃加工)","數量":"430","來源廠商":"伍輝","日期":"2022/10/13","下一關":"同偉行","地區":"加工","行號":"3"},{"單號":"BY202210120019","料號":"H2300-11","品名":"1!!H230大刀片(無YBICO)","數量":"370","來源廠商":"伍輝","日期":"2022/10/14","下一關":"同偉行","地區":"加工","行號":"3"},{"單號":"BY202210120019","料號":"H2300-11","品名":"1!!H230大刀片(無YBICO)","數量":"330","來源廠商":"伍輝","日期":"2022/10/14","下一關":"同偉行","地區":"加工","行號":"3"},{"單號":"BY202210130005","料號":"H1000-11","品名":"H100大刀片(無YBICO)(槌模)","數量":"1200","來源廠商":"合金","日期":"2022/10/14","下一關":"同偉行","地區":"加工","行號":"6"},{"單號":"MK202209050065","料號":"BD603-01","品名":"#BD603直立架組件","數量":"101","來源廠商":"同偉行","日期":"2022/10/14","下一關":"優進(實進)","地區":"委外","行號":"無"},{"單號":"BY202210140034","料號":"PD100-038","品名":"2!A底板657.2mm(有沖A)","數量":"160","來源廠商":"新鎧","日期":"2022/10/17","下一關":"鴻鎰","地區":"委外","行號":"無"},{"單號":"BY202210140034","料號":"PD100-040","品名":"2!B底板654.4mm(有沖B)","數量":"160","來源廠商":"新鎧","日期":"2022/10/17","下一關":"鴻鎰","地區":"委外","行號":"無"},{"單號":"BY202210140014","料號":"S2600-07Y","品名":"螺母軸毛件(中碳 )","數量":"1590","來源廠商":"里祥","日期":"2022/10/17","下一關":"待發","地區":"待發","行號":"1"},{"單號":"BY202210140013","料號":"S260X-11Y","品名":"#S260本台毛件(無YBICO)(槌模)","數量":"600","來源廠商":"駿泰","日期":"2022/10/17","下一關":"同偉行","地區":"加工","行號":"5"},{"單號":"BY202210140013","料號":"S260X-11Y","品名":"#S260本台毛件(無YBICO)(槌模)","數量":"600","來源廠商":"駿泰","日期":"2022/10/17","下一關":"同偉行","地區":"加工","行號":"5"},{"單號":"BY202210140013","料號":"S260X-11Y","品名":"#S260本台毛件(無YBICO)(槌模)","數量":"600","來源廠商":"駿泰","日期":"2022/10/17","下一關":"同偉行","地區":"加工","行號":"5"},{"單號":"BY202210140013","料號":"S260X-11Y","品名":"#S260本台毛件(無YBICO)(槌模)","數量":"600","來源廠商":"駿泰","日期":"2022/10/17","下一關":"同偉行","地區":"加工","行號":"5"},{"單號":"BY202210140013","料號":"S260X-11Y","品名":"#S260本台毛件(無YBICO)(槌模)","數量":"488","來源廠商":"駿泰","日期":"2022/10/17","下一關":"同偉行","地區":"加工","行號":"5"},{"單號":"BY202210140031","料號":"T341N0-00-A10","品名":"T341白片刀片直角片組件","數量":"52","來源廠商":"黃秀滿","日期":"2022/10/17","下一關":"2F4000","地區":"2F","行號":"2"},{"單號":"BY202210140027","料號":"S2900Y-01Y","品名":"#手柄毛件(YBICO)","數量":"306","來源廠商":"頂順","日期":"2022/10/17","下一關":"同偉行","地區":"加工","行號":"6"},{"單號":"BY202210140027","料號":"S2900Y-01Y","品名":"#手柄毛件(YBICO)","數量":"420","來源廠商":"頂順","日期":"2022/10/17","下一關":"同偉行","地區":"加工","行號":"6"},{"單號":"BY202210140027","料號":"S2900Y-01Y","品名":"#手柄毛件(YBICO)","數量":"420","來源廠商":"頂順","日期":"2022/10/17","下一關":"同偉行","地區":"加工","行號":"6"},{"單號":"BY202210140027","料號":"S2900Y-01Y","品名":"#手柄毛件(YBICO)","數量":"520","來源廠商":"頂順","日期":"2022/10/17","下一關":"同偉行","地區":"加工","行號":"6"},{"單號":"BY202210140027","料號":"S2900Y-01Y","品名":"#手柄毛件(YBICO)","數量":"520","來源廠商":"頂順","日期":"2022/10/17","下一關":"同偉行","地區":"加工","行號":"6"},{"單號":"BY202210140024","料號":"H3050-15","品名":"1!!H305直刀(打2)","數量":"50","來源廠商":"伍輝","日期":"2022/10/18","下一關":"合金","地區":"待發","行號":"3"},{"單號":"BY202210170010","料號":"P3100B-01Y","品名":"3!P310藍台毛件(YBICO)(RAL#5015)","數量":"819","來源廠商":"冠承","日期":"2022/10/18","下一關":"同偉行","地區":"加工","行號":"7"},{"單號":"BY202210170010","料號":"P3100B-01Y","品名":"3!P310藍台毛件(YBICO)(RAL#5015)","數量":"800","來源廠商":"冠承","日期":"2022/10/18","下一關":"同偉行","地區":"加工","行號":"7"},{"單號":"BY202210110013","料號":"P1160-28X","品名":"P116鋁柄鑄件","數量":"2750","來源廠商":"億峰富(蕎鋒)","日期":"2022/10/11","下一關":"待發","地區":"B1-C","行號":"2"},{"單號":"BY202210110013","料號":"P1160-28X","品名":"P116鋁柄鑄件","數量":"2379","來源廠商":"億峰富(蕎鋒)","日期":"2022/10/11","下一關":"待發","地區":"B1-C","行號":"2"},{"單號":"BY202210140040","料號":"T283T0-LPE-A10","品名":"T283PANTONE320C刀架PP片印et水","數量":"1296","來源廠商":"陳黃尾春","日期":"2022/10/17","下一關":"2F","地區":"2F","行號":"3"},{"單號":"BY202210140040","料號":"T520N0-S0-A10","品名":"T520灰刀架白片組件","數量":"1440","來源廠商":"陳黃尾春","日期":"2022/10/17","下一關":"2F","地區":"2F","行號":"3"},{"單號":"BY202210140039","料號":"T28200-SY-A10","品名":"T282灰刀架YBICO組件","數量":"124","來源廠商":"鄒智平","日期":"2022/10/17","下一關":"2F","地區":"2F","行號":"4"},{"單號":"BY202210140038","料號":"T282R0-SY-A10","品名":"T282灰刀架YBICO黃PPR組件","數量":"480","來源廠商":"趙美珠","日期":"2022/10/17","下一關":"2F","地區":"2F","行號":"5"},{"單號":"BY202210140038","料號":"T282T0-S0-A10","品名":"T282灰刀架透明片黑TPR組件(無YBICO)","數量":"480","來源廠商":"趙美珠","日期":"2022/10/17","下一關":"2F","地區":"2F","行號":"5"},{"單號":"BY202210140024","料號":"S2680-01Y","品名":"2!S268活動蓋毛件(打8)","數量":"1050","來源廠商":"伍輝","日期":"2022/10/18","下一關":"同偉行","地區":"加工","行號":"3"},{"單號":"BY202210180010","料號":"S2200-35","品名":"3!S220新排齒(電鎳)","數量":"442","來源廠商":"金彰","日期":"2022/10/18","下一關":"同偉行","地區":"加工","行號":"5"},{"單號":"BY202210170019","料號":"CA610B-01","品名":"#CA610台架組件(藍漆)","數量":"120","來源廠商":"山杰","日期":"2022/10/18","下一關":"B14000","地區":"B1-C","行號":"7"},{"單號":"BY202210170019","料號":"CA610B-01","品名":"#CA610台架組件(藍漆)","數量":"61","來源廠商":"山杰","日期":"2022/10/18","下一關":"B14000","地區":"B1-備料","行號":"無"},{"單號":"BY202210180013","料號":"PD300-001","品名":"#PD300切台本體組件(灰1798及03JT)","數量":"100","來源廠商":"森太","日期":"2022/10/18","下一關":"同偉行","地區":"加工","行號":"3"},{"單號":"BY202210180013","料號":"PD300-001","品名":"#PD300切台本體組件(灰1798及03JT)","數量":"100","來源廠商":"森太","日期":"2022/10/18","下一關":"同偉行","地區":"加工","行號":"3"},{"單號":"BY202210180022","料號":"BD603-04","品名":"BD603直立管牙條","數量":"179","來源廠商":"全偉","日期":"2022/10/18","下一關":"優進(實進)","地區":"加工","行號":"5"},{"單號":"BY202210180025","料號":"PQ300H-28Y","品名":"PQ300黑手柄毛件","數量":"979","來源廠商":"冠承","日期":"2022/10/19","下一關":"同偉行","地區":"加工","行號":"5"},{"單號":"BY202210170018","料號":"W1000-04X","品名":"W100雙彎鐵管1*1.4T*403mmL毛件","數量":"706","來源廠商":"鴻隆慶","日期":"2022/10/18","下一關":"待發","地區":"5F","行號":"無"},{"單號":"BY202210170020","料號":"CA350-01","品名":"#藍台架組件","數量":"2","來源廠商":"山杰","日期":"2022/10/18","下一關":"B14000","地區":"B1-B","行號":"5"},{"單號":"BY202208220038","料號":"CA501H-08","品名":"#CA501黑台架組件(無焊帶盤心)","數量":"69","來源廠商":"山杰","日期":"2022/08/23","下一關":"B1","地區":"B1-備料","行號":"無"},{"單號":"BY202210180018","料號":"P2600-02Y","品名":"P260本台毛件(多用途)","數量":"214","來源廠商":"冠億","日期":"2022/10/19","下一關":"待發","地區":"B1-C","行號":"無"},{"單號":"BY202210180018","料號":"P2600-02Y","品名":"P260本台毛件(多用途)","數量":"224","來源廠商":"冠億","日期":"2022/10/19","下一關":"待發","地區":"B1-C","行號":"無"},{"單號":"BY202203280013","料號":"CB720H-11","品名":"#CB720黑台架組件","數量":"10","來源廠商":"山杰","日期":"2022/03/29","下一關":"山杰","地區":"B1-B","行號":"2"},{"單號":"BY202210180018","料號":"P2600-02Y","品名":"P260本台毛件(多用途)","數量":"170","來源廠商":"冠億","日期":"2022/10/19","下一關":"待發","地區":"B1-C","行號":"無"},{"單號":"BY202210180018","料號":"P2600-02Y","品名":"P260本台毛件(多用途)","數量":"223","來源廠商":"冠億","日期":"2022/10/19","下一關":"待發","地區":"B1-C","行號":"無"},{"單號":"BY202210180018","料號":"P2600-02Y","品名":"P260本台毛件(多用途)","數量":"209","來源廠商":"冠億","日期":"2022/10/19","下一關":"待發","地區":"B1-C","行號":"無"},{"單號":"BY202210190009","料號":"T52000-DSM-B22","品名":"T520灰柄紫藍邊蓋印白Manutan組件","數量":"1440","來源廠商":"柯榮華","日期":"2022/10/19","下一關":"2F","地區":"2F","行號":"2"},{"單號":"BY202210190009","料號":"T28200-DSM-B22","品名":"T282灰柄紫藍邊蓋印白Manutan組件","數量":"576","來源廠商":"柯榮華","日期":"2022/10/19","下一關":"2F","地區":"2F","行號":"2"},{"單號":"BY202210170025","料號":"P1620-62","品名":"P162長柄(槌模鍛件)","數量":"1200","來源廠商":"晉邑(進溢)","日期":"2022/10/19","下一關":"3F4000","地區":"3F","行號":"1"},{"單號":"BY202210170025","料號":"P1620-62","品名":"P162長柄(槌模鍛件)","數量":"1190","來源廠商":"晉邑(進溢)","日期":"2022/10/19","下一關":"3F4000","地區":"3F","行號":"1"},{"單號":"BY202210170025","料號":"P1620-63","品名":"P162小手柄(槌模鍛件)","數量":"1400","來源廠商":"晉邑(進溢)","日期":"2022/10/19","下一關":"3F4000","地區":"3F","行號":"1"},{"單號":"BY202210170025","料號":"P1620-62","品名":"P162長柄(槌模鍛件)","數量":"1200","來源廠商":"晉邑(進溢)","日期":"2022/10/19","下一關":"3F4000","地區":"3F","行號":"1"},{"單號":"MK202209160005","料號":"H2300-11","品名":"1!!H230大刀片(無YBICO)","數量":"729","來源廠商":"同偉行","日期":"2022/10/19","下一關":"3F4000","地區":"3F","行號":"1"},{"單號":"BY202210190008","料號":"H3000-08","品名":"公連桿柄組件","數量":"1126","來源廠商":"優進(實進)","日期":"2022/10/20","下一關":"鴻鎰","地區":"委外","行號":"無"},{"單號":"BY202210190008","料號":"H3000-09","品名":"母連桿柄組件","數量":"954","來源廠商":"優進(實進)","日期":"2022/10/20","下一關":"鴻鎰","地區":"委外","行號":"無"},{"單號":"BY202210190023","料號":"P3100A-01","品名":"P310暗紅台組件(RAL3020)","數量":"1079","來源廠商":"和峰","日期":"2022/10/20","下一關":"鴻鎰","地區":"委外","行號":"無"},{"單號":"BY202210200009","料號":"T72000-S2","品名":"T720 灰色 2'' 印黑GLOBAL","數量":"720","來源廠商":"邱博鴻","日期":"2022/10/20","下一關":"2F","地區":"2F","行號":"4"},{"單號":"BY202210200009","料號":"T72000-S","品名":"灰色 2 MIT","數量":"199","來源廠商":"邱博鴻","日期":"2022/10/20","下一關":"2F","地區":"2F","行號":"4"},{"單號":"BY202210200009","料號":"T26000-G0-B22","品名":"T260柄綠邊蓋組件","數量":"480","來源廠商":"邱博鴻","日期":"2022/10/20","下一關":"2F","地區":"2F","行號":"6"},{"單號":"BY202210200015","料號":"T282DM-FL2-B21","品名":"T282(e-tape)Reflex BlueC柄鐵接","數量":"171","來源廠商":"柯榮華","日期":"2022/10/20","下一關":"2F","地區":"2F","行號":"8"},{"單號":"BY202210200020","料號":"S260X-11Y","品名":"#S260本台毛件(無YBICO)(槌模)","數量":"110","來源廠商":"駿泰","日期":"2022/10/20","下一關":"同偉行","地區":"加工","行號":"4"},{"單號":"BY202210200020","料號":"S260X-11Y","品名":"#S260本台毛件(無YBICO)(槌模)","數量":"600","來源廠商":"駿泰","日期":"2022/10/20","下一關":"同偉行","地區":"加工","行號":"4"},{"單號":"BY202210200020","料號":"S260X-11Y","品名":"#S260本台毛件(無YBICO)(槌模)","數量":"600","來源廠商":"駿泰","日期":"2022/10/20","下一關":"同偉行","地區":"加工","行號":"4"},{"單號":"BY202210200020","料號":"S260X-11Y","品名":"#S260本台毛件(無YBICO)(槌模)","數量":"600","來源廠商":"駿泰","日期":"2022/10/20","下一關":"同偉行","地區":"加工","行號":"4"},{"單號":"BY202210200020","料號":"S260X-11Y","品名":"#S260本台毛件(無YBICO)(槌模)","數量":"600","來源廠商":"駿泰","日期":"2022/10/20","下一關":"同偉行","地區":"加工","行號":"4"},{"單號":"BY202210200020","料號":"S260X-11Y","品名":"#S260本台毛件(無YBICO)(槌模)","數量":"600","來源廠商":"駿泰","日期":"2022/10/20","下一關":"同偉行","地區":"加工","行號":"4"},{"單號":"BY202210120013","料號":"T25100-S0-B21","品名":"T251灰柄無MIT組件","數量":"748","來源廠商":"邱博鴻","日期":"2022/10/12","下一關":"2F","地區":"2F","行號":"7"},{"單號":"BY202210190024","料號":"CB720H-11","品名":"#CB720黑台架組件","數量":"34","來源廠商":"鴻鎰","日期":"2022/10/21","下一關":"B14000","地區":"B1-C","行號":"7"},{"單號":"BY202210190024","料號":"CB720H-11","品名":"#CB720黑台架組件","數量":"52","來源廠商":"鴻鎰","日期":"2022/10/21","下一關":"B14000","地區":"B1-C","行號":"7"},{"單號":"BY202210200025","料號":"CA500Y-47","品名":"(依訂單烤漆) CA500黃母帶盤ID400*OD635mm","數量":"51","來源廠商":"鴻鎰","日期":"2022/10/21","下一關":"B14000","地區":"B1-A","行號":"1"},{"單號":"BY202210200025","料號":"CA100Y-51","品名":"(依訂單烤漆)#CA100黃公帶盤組件ID200*OD610mm(4小孔","數量":"75","來源廠商":"鴻鎰","日期":"2022/10/21","下一關":"B14000","地區":"B1-A","行號":"1"},{"單號":"BY202210200025","料號":"CA100Y-24","品名":"(依訂單烤漆)#黃母帶盤400mm*OD610mm","數量":"75","來源廠商":"鴻鎰","日期":"2022/10/21","下一關":"B14000","地區":"B1-A","行號":"1"},{"單號":"BY202210200026","料號":"CA400Y-20","品名":"(依訂單烤漆) CA400黃公帶盤組件OD710mm","數量":"10","來源廠商":"鴻鎰","日期":"2022/10/21","下一關":"B14000","地區":"B1-A","行號":"1"},{"單號":"BY202210200026","料號":"CA400Y-25","品名":"(依訂單烤漆) #CA400黃母帶盤組件OD710mm","數量":"15","來源廠商":"鴻鎰","日期":"2022/10/21","下一關":"B14000","地區":"B1-A","行號":"1"},{"單號":"BY202210200026","料號":"CA500Y-41","品名":"(依訂單烤漆)#CA500黃公帶盤組件ID400*OD635mm","數量":"53","來源廠商":"鴻鎰","日期":"2022/10/21","下一關":"B14000","地區":"B1-A","行號":"1"},{"單號":"BY202210210004","料號":"H3050-15","品名":"1!!H305直刀(打2)","數量":"589","來源廠商":"合金","日期":"2022/10/21","下一關":"同偉行","地區":"加工","行號":"2"},{"單號":"BY202210210004","料號":"H3050-15","品名":"1!!H305直刀(打2)","數量":"459","來源廠商":"合金","日期":"2022/10/21","下一關":"同偉行","地區":"加工","行號":"2"},{"單號":"BY202210210004","料號":"H3050-15","品名":"1!!H305直刀(打2)","數量":"336","來源廠商":"合金","日期":"2022/10/21","下一關":"同偉行","地區":"加工","行號":"2"},{"單號":"BY202210190013","料號":"SL201-99","品名":"SL201底板(槌膜)(有鎖護墊孔)(打2)","數量":"79","來源廠商":"有宏","日期":"2022/10/20","下一關":"晶幃","地區":"加工","行號":"2"},{"單號":"BY202210190013","料號":"SL221-99","品名":"SL221底板(有鎖護墊孔)(槌膜)(打221)","數量":"18","來源廠商":"有宏","日期":"2022/10/20","下一關":"晶幃","地區":"加工","行號":"2"},{"單號":"BY202210210020","料號":"S2400-21","品名":"3!S240大手柄(電鎳)","數量":"1057","來源廠商":"亞柏","日期":"2022/10/21","下一關":"同偉行","地區":"加工","行號":"6"},{"單號":"BY202210210020","料號":"S2900-12","品名":"#(可用S2910-12)S290花輪(YBICO)","數量":"2277","來源廠商":"亞柏","日期":"2022/10/21","下一關":"文生","地區":"委外","行號":"無"},{"單號":"BY202210210013","料號":"S2900-08Y","品名":"#S290合蓋毛件","數量":"900","來源廠商":"錩盛","日期":"2022/10/21","下一關":"同偉行","地區":"加工","行號":"7"},{"單號":"BY202210210013","料號":"S2900-08Y","品名":"#S290合蓋毛件","數量":"900","來源廠商":"錩盛","日期":"2022/10/21","下一關":"同偉行","地區":"加工","行號":"7"},{"單號":"BY202210210013","料號":"S2900-08Y","品名":"#S290合蓋毛件","數量":"900","來源廠商":"錩盛","日期":"2022/10/21","下一關":"同偉行","地區":"加工","行號":"7"},{"單號":"BY202210210031","料號":"H3050-11","品名":"H305鉤子","數量":"2732","來源廠商":"伍輝","日期":"2022/10/21","下一關":"國榮","地區":"委外","行號":"無"},{"單號":"BY202210210027","料號":"H2110-12","品名":"1!!H211小刀片(YBICO)","數量":"1410","來源廠商":"仲博","日期":"2022/10/24","下一關":"合金","地區":"委外","行號":"無"},{"單號":"BY202210210027","料號":"H3050-15","品名":"1!!H305直刀(打2)","數量":"500","來源廠商":"仲博","日期":"2022/10/24","下一關":"伍輝","地區":"委外","行號":"無"},{"單號":"BY202206290045","料號":"CA610-06","品名":"鐵管7/8*1.5*300","數量":"139","來源廠商":"鴻隆慶","日期":"2022/07/01","下一關":"待發","地區":"3F","行號":"2"},{"單號":"BY202210210016","料號":"T52100-H1-A16","品名":"T521黑刀架透明片組件(3M)","數量":"1440","來源廠商":"鄒智平","日期":"2022/10/21","下一關":"2F","地區":"2F","行號":"3"},{"單號":"BY202210210016","料號":"T563N0-00-A10","品名":"灰刀座伸縮刀片白片","數量":"240","來源廠商":"鄒智平","日期":"2022/10/21","下一關":"2F","地區":"2F","行號":"3"},{"單號":"BY202210210016","料號":"T23100-0P0-A10","品名":"T231灰刀座PP白片組件","數量":"480","來源廠商":"鄒智平","日期":"2022/10/21","下一關":"2F","地區":"2F","行號":"3"},{"單號":"BY202210210016","料號":"T23000-Y0-A10","品名":"T230YBICO刀片直角片組件","數量":"65","來源廠商":"鄒智平","日期":"2022/10/21","下一關":"2F","地區":"2F","行號":"3"},{"單號":"BY202210210016","料號":"T52100-S0-A10","品名":"T521灰刀架YBICO組件","數量":"20","來源廠商":"鄒智平","日期":"2022/10/21","下一關":"2F","地區":"2F","行號":"3"},{"單號":"BY202210210018","料號":"T23500-0P0-A10","品名":"T235灰刀座PP片組件","數量":"768","來源廠商":"陳黃尾春","日期":"2022/10/21","下一關":"2F","地區":"2F","行號":"2"},{"單號":"BY202210210018","料號":"T230N0-00-A10","品名":"T230白片刀片直角片組件","數量":"576","來源廠商":"陳黃尾春","日期":"2022/10/21","下一關":"2F","地區":"2F","行號":"2"},{"單號":"BY202210210018","料號":"T52000-SG-A10","品名":"T520灰刀架PC片印GL組件","數量":"400","來源廠商":"陳黃尾春","日期":"2022/10/21","下一關":"2F","地區":"2F","行號":"2"},{"單號":"BY202210210017","料號":"T282D0-AH8-B22","品名":"T282黑紅柄印EA暗紅邊蓋組件","數量":"3000","來源廠商":"柯榮華","日期":"2022/10/21","下一關":"2F","地區":"2F","行號":"7"},{"單號":"BY202210210017","料號":"T282D0-AH8-B22","品名":"T282黑紅柄印EA暗紅邊蓋組件","數量":"2400","來源廠商":"柯榮華","日期":"2022/10/21","下一關":"2F","地區":"2F","行號":"7"},{"單號":"BY202210210032","料號":"H3050-15","品名":"1!!H305直刀(打2)","數量":"1000","來源廠商":"伍輝","日期":"2022/10/24","下一關":"合金","地區":"委外","行號":"無"},{"單號":"BY202210210032","料號":"S2400-08","品名":"長薄鳥","數量":"3319","來源廠商":"伍輝","日期":"2022/10/24","下一關":"國榮","地區":"委外","行號":"無"},{"單號":"BY202210210032","料號":"S2400-07","品名":"短薄鳥","數量":"3320","來源廠商":"伍輝","日期":"2022/10/24","下一關":"國榮","地區":"委外","行號":"無"},{"單號":"BY202210210033","料號":"CA247H-01","品名":"CA247黑台架組件(先用CA259H-01,再用CA247H-03)","數量":"81","來源廠商":"山杰","日期":"2022/10/24","下一關":"B14000","地區":"B1-A","行號":"1"}]